// converted by version 1.3
// on Thu Jan 01 20:29:33 ICT 2026

.package thegym {
	.aid 0xAA:0xBB:0xCC:0xDD:0xEE;
	.version 1.0;

	.imports {
		0xA0:0x0:0x0:0x0:0x62:0x1:0x1 1.2;		//javacard/framework
		0xA0:0x0:0x0:0x0:0x62:0x1:0x2 1.2;		//javacard/security
		0xA0:0x0:0x0:0x0:0x62:0x2:0x1 1.2;		//javacardx/crypto
	}

	.applet {
		0xAA:0xBB:0xCC:0xDD:0xEE:0x0 thegym;
	}

	.constantPool {
		// 0
		instanceFieldRef 0.9 thegym/pin;
		// 1
		instanceFieldRef byte[] thegym/pinBuffer;
		// 2
		instanceFieldRef byte[] thegym/userData;
		// 3
		instanceFieldRef byte[] thegym/avatarData;
		// 4
		instanceFieldRef byte[] thegym/recoverySDT;
		// 5
		instanceFieldRef byte[] thegym/transactionHistory;
		// 6
		instanceFieldRef byte[] thegym/tempBuffer;
		// 7
		instanceFieldRef byte[] thegym/tempBuffer2;
		// 8
		instanceFieldRef byte[] thegym/masterKeyBuffer;
		// 9
		instanceFieldRef byte[] thegym/masterIvBuffer;
		// 10
		instanceFieldRef byte[] thegym/sessionKeyBuffer;
		// 11
		instanceFieldRef byte[] thegym/sessionIvBuffer;
		// 12
		instanceFieldRef byte[] thegym/hashBuffer;
		// 13
		instanceFieldRef 1.11 thegym/sha1;
		// 14
		instanceFieldRef 1.14 thegym/secureRandom;
		// 15
		instanceFieldRef 2.1 thegym/aesCipher;
		// 16
		instanceFieldRef 1.20 thegym/masterKey;
		// 17
		instanceFieldRef 1.20 thegym/sessionAesKey;
		// 18
		instanceFieldRef 1.16 thegym/rsaKeyPair;
		// 19
		instanceFieldRef 1.9 thegym/rsaPublicKey;
		// 20
		instanceFieldRef 1.8 thegym/rsaPrivateKey;
		// 21
		instanceFieldRef 2.1 thegym/rsaCipher;
		// 22
		instanceFieldRef 1.15 thegym/rsaSignature;
		// 23
		instanceFieldRef boolean thegym/cryptoInitialized;
		// 24
		instanceFieldRef boolean thegym/rsaKeysGenerated;
		// 25
		instanceFieldRef boolean thegym/masterKeyDerived;
		// 26
		instanceFieldRef short thegym/userDataLen;
		// 27
		instanceFieldRef short thegym/avatarCurrentSize;
		// 28
		instanceFieldRef byte thegym/recoverySDTLen;
		// 29
		instanceFieldRef short thegym/balance;
		// 30
		instanceFieldRef byte thegym/historyIndex;
		// 31
		staticMethodRef 0.3.0()V;		// javacard/framework/Applet.<init>()V
		// 32
		classRef 0.9;		// javacard/framework/OwnerPIN
		// 33
		staticMethodRef 0.9.0(BB)V;		// javacard/framework/OwnerPIN.<init>(BB)V
		// 34
		staticMethodRef thegym/<init>()V;
		// 35
		virtualMethodRef 0.9.8([BSB)V;		// javacard/framework/OwnerPIN.update([BSB)V
		// 36
		classRef thegym;
		// 37
		virtualMethodRef 0.3.1()V;		// javacard/framework/Applet.register()V
		// 38
		classRef 1.12;		// javacard/security/CryptoException
		// 39
		staticMethodRef 1.11.0(BZ)Ljavacard/security/MessageDigest;;		// javacard/security/MessageDigest.getInstance(BZ)Ljavacard/security/MessageDigest;
			.descriptor	Ljavacard/security/MessageDigest;	1.11;

		// 40
		staticMethodRef 1.14.0(B)Ljavacard/security/RandomData;;		// javacard/security/RandomData.getInstance(B)Ljavacard/security/RandomData;
			.descriptor	Ljavacard/security/RandomData;	1.14;

		// 41
		staticMethodRef 2.1.0(BZ)Ljavacardx/crypto/Cipher;;		// javacardx/crypto/Cipher.getInstance(BZ)Ljavacardx/crypto/Cipher;
			.descriptor	Ljavacardx/crypto/Cipher;	2.1;

		// 42
		staticMethodRef 1.13.0(BSZ)Ljavacard/security/Key;;		// javacard/security/KeyBuilder.buildKey(BSZ)Ljavacard/security/Key;
			.descriptor	Ljavacard/security/Key;	1.0;

		// 43
		classRef 1.20;		// javacard/security/AESKey
		// 44
		classRef 1.16;		// javacard/security/KeyPair
		// 45
		staticMethodRef 1.16.0(BS)V;		// javacard/security/KeyPair.<init>(BS)V
		// 46
		staticMethodRef 1.15.0(BZ)Ljavacard/security/Signature;;		// javacard/security/Signature.getInstance(BZ)Ljavacard/security/Signature;
			.descriptor	Ljavacard/security/Signature;	1.15;

		// 47
		virtualMethodRef 1.11.4()V;		// javacard/security/MessageDigest.reset()V
		// 48
		virtualMethodRef 1.11.5([BSS)V;		// javacard/security/MessageDigest.update([BSS)V
		// 49
		virtualMethodRef 1.11.1([BSS[BS)S;		// javacard/security/MessageDigest.doFinal([BSS[BS)S
		// 50
		staticMethodRef 0.16.1([BS[BSS)S;		// javacard/framework/Util.arrayCopy([BS[BSS)S
		// 51
		staticMethodRef 0.16.3([BSSB)S;		// javacard/framework/Util.arrayFillNonAtomic([BSSB)S
		// 52
		virtualMethodRef 0.3.3()Z;		// javacard/framework/Applet.selectingApplet()Z
		// 53
		virtualMethodRef 0.10.1()[B;		// javacard/framework/APDU.getBuffer()[B
		// 54
		virtualMethodRef 0.9.2()B;		// javacard/framework/OwnerPIN.getTriesRemaining()B
		// 55
		staticMethodRef 0.7.1(S)V;		// javacard/framework/ISOException.throwIt(S)V
		// 56
		staticMethodRef thegym/processVerifyPin(Ljavacard/framework/APDU;)V;
			.descriptor	Ljavacard/framework/APDU;	0.10;

		// 57
		staticMethodRef thegym/processVerifyPinSecure(Ljavacard/framework/APDU;)V;
			.descriptor	Ljavacard/framework/APDU;	0.10;

		// 58
		staticMethodRef thegym/processChangePin(Ljavacard/framework/APDU;)V;
			.descriptor	Ljavacard/framework/APDU;	0.10;

		// 59
		staticMethodRef thegym/processChangePinSecure(Ljavacard/framework/APDU;)V;
			.descriptor	Ljavacard/framework/APDU;	0.10;

		// 60
		staticMethodRef thegym/processSetRecoveryPhone(Ljavacard/framework/APDU;)V;
			.descriptor	Ljavacard/framework/APDU;	0.10;

		// 61
		staticMethodRef thegym/processUnblockPin(Ljavacard/framework/APDU;)V;
			.descriptor	Ljavacard/framework/APDU;	0.10;

		// 62
		staticMethodRef thegym/processUpdateInfoEncaps(Ljavacard/framework/APDU;)V;
			.descriptor	Ljavacard/framework/APDU;	0.10;

		// 63
		staticMethodRef thegym/processGetInfoEncaps(Ljavacard/framework/APDU;)V;
			.descriptor	Ljavacard/framework/APDU;	0.10;

		// 64
		staticMethodRef thegym/processUploadAvatarEncaps(Ljavacard/framework/APDU;)V;
			.descriptor	Ljavacard/framework/APDU;	0.10;

		// 65
		staticMethodRef thegym/processGetAvatarEncaps(Ljavacard/framework/APDU;)V;
			.descriptor	Ljavacard/framework/APDU;	0.10;

		// 66
		staticMethodRef thegym/processTransaction(Ljavacard/framework/APDU;Z)V;
			.descriptor	Ljavacard/framework/APDU;	0.10;

		// 67
		staticMethodRef thegym/processCheckBalance(Ljavacard/framework/APDU;)V;
			.descriptor	Ljavacard/framework/APDU;	0.10;

		// 68
		staticMethodRef thegym/processGetHistory(Ljavacard/framework/APDU;)V;
			.descriptor	Ljavacard/framework/APDU;	0.10;

		// 69
		staticMethodRef thegym/processInitCrypto(Ljavacard/framework/APDU;)V;
			.descriptor	Ljavacard/framework/APDU;	0.10;

		// 70
		staticMethodRef thegym/processGetStatus(Ljavacard/framework/APDU;)V;
			.descriptor	Ljavacard/framework/APDU;	0.10;

		// 71
		staticMethodRef thegym/processSetSessionKey(Ljavacard/framework/APDU;)V;
			.descriptor	Ljavacard/framework/APDU;	0.10;

		// 72
		staticMethodRef thegym/processGenRSAKeyPair(Ljavacard/framework/APDU;)V;
			.descriptor	Ljavacard/framework/APDU;	0.10;

		// 73
		staticMethodRef thegym/processGetRSAPublic(Ljavacard/framework/APDU;)V;
			.descriptor	Ljavacard/framework/APDU;	0.10;

		// 74
		staticMethodRef thegym/processRSAEncrypt(Ljavacard/framework/APDU;)V;
			.descriptor	Ljavacard/framework/APDU;	0.10;

		// 75
		staticMethodRef thegym/processRSADecrypt(Ljavacard/framework/APDU;)V;
			.descriptor	Ljavacard/framework/APDU;	0.10;

		// 76
		staticMethodRef thegym/processRSASign(Ljavacard/framework/APDU;)V;
			.descriptor	Ljavacard/framework/APDU;	0.10;

		// 77
		staticMethodRef thegym/processRSAVerify(Ljavacard/framework/APDU;)V;
			.descriptor	Ljavacard/framework/APDU;	0.10;

		// 78
		staticMethodRef thegym/processHashData(Ljavacard/framework/APDU;)V;
			.descriptor	Ljavacard/framework/APDU;	0.10;

		// 79
		staticMethodRef thegym/processUpdateInfoLegacy(Ljavacard/framework/APDU;)V;
			.descriptor	Ljavacard/framework/APDU;	0.10;

		// 80
		staticMethodRef thegym/processGetInfoLegacy(Ljavacard/framework/APDU;)V;
			.descriptor	Ljavacard/framework/APDU;	0.10;

		// 81
		staticMethodRef thegym/processUploadAvatarLegacy(Ljavacard/framework/APDU;)V;
			.descriptor	Ljavacard/framework/APDU;	0.10;

		// 82
		staticMethodRef thegym/processGetAvatarLegacy(Ljavacard/framework/APDU;)V;
			.descriptor	Ljavacard/framework/APDU;	0.10;

		// 83
		virtualMethodRef 0.9.4()Z;		// javacard/framework/OwnerPIN.isValidated()Z
		// 84
		virtualMethodRef 0.10.8(SS)V;		// javacard/framework/APDU.setOutgoingAndSend(SS)V
		// 85
		virtualMethodRef 0.10.6()S;		// javacard/framework/APDU.setIncomingAndReceive()S
		// 86
		staticMethodRef thegym/decapsulateSessionKey([BS)Z;
		// 87
		staticMethodRef thegym/initCrypto()Z;
		// 88
		virtualMethodRef 0.9.1([BSB)Z;		// javacard/framework/OwnerPIN.check([BSB)Z
		// 89
		staticMethodRef thegym/deriveMasterKeyFromPIN([BSS)V;
		// 90
		virtualMethodRef 2.1.3(Ljavacard/security/Key;B)V;		// javacardx/crypto/Cipher.init(Ljavacard/security/Key;B)V
			.descriptor	Ljavacard/security/Key;	1.0;

		// 91
		virtualMethodRef 2.1.1([BSS[BS)S;		// javacardx/crypto/Cipher.doFinal([BSS[BS)S
		// 92
		staticMethodRef 0.8.13(SB)[B;		// javacard/framework/JCSystem.makeTransientByteArray(SB)[B
		// 93
		staticMethodRef thegym/reEncryptData([BSLjavacard/security/AESKey;[B)V;
			.descriptor	Ljavacard/security/AESKey;	1.20;

		// 94
		staticMethodRef thegym/reEncryptAvatar(Ljavacard/security/AESKey;[B)V;
			.descriptor	Ljavacard/security/AESKey;	1.20;

		// 95
		virtualMethodRef 2.1.4(Ljavacard/security/Key;B[BSS)V;		// javacardx/crypto/Cipher.init(Ljavacard/security/Key;B[BSS)V
			.descriptor	Ljavacard/security/Key;	1.0;

		// 96
		staticMethodRef 0.16.0([BS[BSS)B;		// javacard/framework/Util.arrayCompare([BS[BSS)B
		// 97
		virtualMethodRef 0.9.6()V;		// javacard/framework/OwnerPIN.resetAndUnblock()V
		// 98
		virtualMethodRef 1.16.1()V;		// javacard/security/KeyPair.genKeyPair()V
		// 99
		virtualMethodRef 1.16.3()Ljavacard/security/PublicKey;;		// javacard/security/KeyPair.getPublic()Ljavacard/security/PublicKey;
			.descriptor	Ljavacard/security/PublicKey;	1.3;

		// 100
		classRef 1.9;		// javacard/security/RSAPublicKey
		// 101
		virtualMethodRef 1.16.2()Ljavacard/security/PrivateKey;;		// javacard/security/KeyPair.getPrivate()Ljavacard/security/PrivateKey;
			.descriptor	Ljavacard/security/PrivateKey;	1.2;

		// 102
		classRef 1.8;		// javacard/security/RSAPrivateKey
		// 103
		virtualMethodRef 1.15.3(Ljavacard/security/Key;B)V;		// javacard/security/Signature.init(Ljavacard/security/Key;B)V
			.descriptor	Ljavacard/security/Key;	1.0;

		// 104
		virtualMethodRef 1.15.5([BSS[BS)S;		// javacard/security/Signature.sign([BSS[BS)S
		// 105
		staticMethodRef 0.16.4([BS)S;		// javacard/framework/Util.getShort([BS)S
		// 106
		virtualMethodRef 1.15.7([BSS[BSS)Z;		// javacard/security/Signature.verify([BSS[BSS)Z
		// 107
		staticMethodRef 0.16.6([BSS)S;		// javacard/framework/Util.setShort([BSS)S
		// 108
		staticMethodRef thegym/reEncryptAvatarWithMasterKey(S)V;
		// 109
		staticMethodRef 0.8.1()V;		// javacard/framework/JCSystem.beginTransaction()V
		// 110
		staticMethodRef 0.8.0()V;		// javacard/framework/JCSystem.abortTransaction()V
		// 111
		staticMethodRef thegym/logTransaction(BS)V;
		// 112
		staticMethodRef 0.8.2()V;		// javacard/framework/JCSystem.commitTransaction()V
	}

	.class public thegym 0 extends 0.3 {		// extends javacard/framework/Applet

		.fields {
			private 0.9 pin 0;		// Ljavacard/framework/OwnerPIN;
			private byte[] pinBuffer 1;		// [B
			private byte[] recoverySDT 2;		// [B
			private byte[] userData 3;		// [B
			private byte[] avatarData 4;		// [B
			private byte[] transactionHistory 5;		// [B
			private 1.11 sha1 6;		// Ljavacard/security/MessageDigest;
			private 1.14 secureRandom 7;		// Ljavacard/security/RandomData;
			private 2.1 aesCipher 8;		// Ljavacardx/crypto/Cipher;
			private 1.20 masterKey 9;		// Ljavacard/security/AESKey;
			private 1.20 sessionAesKey 10;		// Ljavacard/security/AESKey;
			private 1.16 rsaKeyPair 11;		// Ljavacard/security/KeyPair;
			private 1.9 rsaPublicKey 12;		// Ljavacard/security/RSAPublicKey;
			private 1.8 rsaPrivateKey 13;		// Ljavacard/security/RSAPrivateKey;
			private 2.1 rsaCipher 14;		// Ljavacardx/crypto/Cipher;
			private 1.15 rsaSignature 15;		// Ljavacard/security/Signature;
			private byte[] tempBuffer 16;		// [B
			private byte[] tempBuffer2 17;		// [B
			private byte[] masterKeyBuffer 18;		// [B
			private byte[] masterIvBuffer 19;		// [B
			private byte[] sessionKeyBuffer 20;		// [B
			private byte[] sessionIvBuffer 21;		// [B
			private byte[] hashBuffer 22;		// [B
			private byte recoverySDTLen 23;		// B
			private short userDataLen 24;		// S
			private short avatarCurrentSize 25;		// S
			private short balance 26;		// S
			private byte historyIndex 27;		// B
			private boolean cryptoInitialized 28;		// Z
			private boolean rsaKeysGenerated 29;		// Z
			private boolean masterKeyDerived 30;		// Z
			private static final byte INS_VERIFY_PIN = 16;		// B
			private static final byte INS_CHANGE_PIN = 17;		// B
			private static final byte INS_UNBLOCK_PIN = 18;		// B
			private static final byte INS_VERIFY_PIN_SECURE = 19;		// B
			private static final byte INS_CHANGE_PIN_SECURE = 20;		// B
			private static final byte INS_SET_RECOVERY_PHONE = 21;		// B
			private static final byte INS_UPDATE_INFO = 32;		// B
			private static final byte INS_GET_INFO = 33;		// B
			private static final byte INS_UPLOAD_AVATAR = 34;		// B
			private static final byte INS_GET_AVATAR = 35;		// B
			private static final byte INS_UPDATE_INFO_ENCAPS = 36;		// B
			private static final byte INS_GET_INFO_ENCAPS = 37;		// B
			private static final byte INS_UPLOAD_AVATAR_ENCAPS = 38;		// B
			private static final byte INS_GET_AVATAR_ENCAPS = 39;		// B
			private static final byte INS_TOPUP = 48;		// B
			private static final byte INS_PAYMENT = 49;		// B
			private static final byte INS_CHECK_BALANCE = 50;		// B
			private static final byte INS_GET_HISTORY = 64;		// B
			private static final byte INS_INIT_CRYPTO = 80;		// B
			private static final byte INS_GET_STATUS = 81;		// B
			private static final byte INS_SET_SESSION_KEY = 82;		// B
			private static final byte INS_GEN_RSA_KEYPAIR = 96;		// B
			private static final byte INS_GET_RSA_PUBLIC = 97;		// B
			private static final byte INS_RSA_ENCRYPT = 98;		// B
			private static final byte INS_RSA_DECRYPT = 99;		// B
			private static final byte INS_RSA_SIGN = 100;		// B
			private static final byte INS_RSA_VERIFY = 101;		// B
			private static final byte INS_HASH_DATA = -127;		// B
			private static final byte PIN_MAX_TRIES = 5;		// B
			private static final byte PIN_LENGTH = 6;		// B
			private static final short MAX_INFO_SIZE = 1024;		// S
			private static final short MAX_AVATAR = 10240;		// S
			private static final short RSA_KEY_SIZE = 1024;		// S
			private static final short RSA_BLOCK_SIZE = 128;		// S
			private static final short AES_BLOCK_SIZE = 16;		// S
			private static final short SESSION_KEY_SIZE = 16;		// S
			private static final short IV_SIZE = 16;		// S
			private static final short SHA1_SIZE = 20;		// S
		}

		.publicMethodTable 7 {
			equals(Ljava/lang/Object;)Z;
			register()V;
			register([BSB)V;
			selectingApplet()Z;
			deselect()V;
			getShareableInterfaceObject(Ljavacard/framework/AID;B)Ljavacard/framework/Shareable;;
			select()Z;
			process(Ljavacard/framework/APDU;)V;
		}

		.packageMethodTable 0 {
		}

		.method public static install([BSB)V 0 {
			.stack 2;
			.locals 1;

				L0:	new 36;		// thegym/thegym
					dup;
					invokespecial 34;		// thegym/thegym.<init>()V
					astore_3;
				L1:	aload_3;
					invokevirtual 37;		// javacard/framework/Applet.register()V
					return;
		}

		.method private <init>()V {
			.stack 5;
			.locals 1;

				L0:	aload_0;
					invokespecial 31;		// javacard/framework/Applet.<init>()V
					aload_0;
					new 32;		// javacard/framework/OwnerPIN
					dup;
					sconst_5;
					bspush 6;
					invokespecial 33;		// javacard/framework/OwnerPIN.<init>(BB)V
					putfield_a 0;		// reference thegym/thegym.pin
					bspush 6;
					newarray 11;
					dup;
					sconst_0;
					bspush 49;
					bastore;
					dup;
					sconst_1;
					bspush 50;
					bastore;
					dup;
					sconst_2;
					bspush 51;
					bastore;
					dup;
					sconst_3;
					bspush 52;
					bastore;
					dup;
					sconst_4;
					bspush 53;
					bastore;
					dup;
					sconst_5;
					bspush 54;
					bastore;
					astore_1;
				L1:	getfield_a_this 0;		// reference thegym/thegym.pin
					aload_1;
					sconst_0;
					bspush 6;
					invokevirtual 35;		// javacard/framework/OwnerPIN.update([BSB)V
					aload_0;
					bspush 6;
					newarray 11;
					putfield_a 1;		// reference thegym/thegym.pinBuffer
					aload_0;
					sspush 1024;
					newarray 11;
					putfield_a 2;		// reference thegym/thegym.userData
					aload_0;
					sspush 10240;
					newarray 11;
					putfield_a 3;		// reference thegym/thegym.avatarData
					aload_0;
					bspush 12;
					newarray 11;
					putfield_a 4;		// reference thegym/thegym.recoverySDT
					aload_0;
					bspush 20;
					newarray 11;
					putfield_a 5;		// reference thegym/thegym.transactionHistory
					aload_0;
					sspush 256;
					newarray 11;
					putfield_a 6;		// reference thegym/thegym.tempBuffer
					aload_0;
					sspush 256;
					newarray 11;
					putfield_a 7;		// reference thegym/thegym.tempBuffer2
					aload_0;
					bspush 16;
					newarray 11;
					putfield_a 8;		// reference thegym/thegym.masterKeyBuffer
					aload_0;
					bspush 16;
					newarray 11;
					putfield_a 9;		// reference thegym/thegym.masterIvBuffer
					aload_0;
					bspush 16;
					newarray 11;
					putfield_a 10;		// reference thegym/thegym.sessionKeyBuffer
					aload_0;
					bspush 16;
					newarray 11;
					putfield_a 11;		// reference thegym/thegym.sessionIvBuffer
					aload_0;
					bspush 24;
					newarray 11;
					putfield_a 12;		// reference thegym/thegym.hashBuffer
					aload_0;
					aconst_null;
					putfield_a 13;		// reference thegym/thegym.sha1
					aload_0;
					aconst_null;
					putfield_a 14;		// reference thegym/thegym.secureRandom
					aload_0;
					aconst_null;
					putfield_a 15;		// reference thegym/thegym.aesCipher
					aload_0;
					aconst_null;
					putfield_a 16;		// reference thegym/thegym.masterKey
					aload_0;
					aconst_null;
					putfield_a 17;		// reference thegym/thegym.sessionAesKey
					aload_0;
					aconst_null;
					putfield_a 18;		// reference thegym/thegym.rsaKeyPair
					aload_0;
					aconst_null;
					putfield_a 19;		// reference thegym/thegym.rsaPublicKey
					aload_0;
					aconst_null;
					putfield_a 20;		// reference thegym/thegym.rsaPrivateKey
					aload_0;
					aconst_null;
					putfield_a 21;		// reference thegym/thegym.rsaCipher
					aload_0;
					aconst_null;
					putfield_a 22;		// reference thegym/thegym.rsaSignature
					aload_0;
					sconst_0;
					putfield_b 23;		// boolean thegym/thegym.cryptoInitialized
					aload_0;
					sconst_0;
					putfield_b 24;		// boolean thegym/thegym.rsaKeysGenerated
					aload_0;
					sconst_0;
					putfield_b 25;		// boolean thegym/thegym.masterKeyDerived
					aload_0;
					sconst_0;
					putfield_s 26;		// short thegym/thegym.userDataLen
					aload_0;
					sconst_0;
					putfield_s 27;		// short thegym/thegym.avatarCurrentSize
					aload_0;
					sconst_0;
					putfield_b 28;		// byte thegym/thegym.recoverySDTLen
					aload_0;
					sconst_0;
					putfield_s 29;		// short thegym/thegym.balance
					aload_0;
					sconst_0;
					putfield_b 30;		// byte thegym/thegym.historyIndex
					return;
		}

		.method private initCrypto()Z {
			.stack 5;
			.locals 1;

				L0:	getfield_b_this 23;		// boolean thegym/thegym.cryptoInitialized
					ifeq L2;
				L1:	sconst_1;
					sreturn;
				L2:	aload_0;
					sconst_1;
					sconst_0;
					invokestatic 39;		// javacard/security/MessageDigest.getInstance(BZ)Ljavacard/security/MessageDigest;
					putfield_a 13;		// reference thegym/thegym.sha1
					aload_0;
					sconst_2;
					invokestatic 40;		// javacard/security/RandomData.getInstance(B)Ljavacard/security/RandomData;
					putfield_a 14;		// reference thegym/thegym.secureRandom
					aload_0;
					bspush 13;
					sconst_0;
					invokestatic 41;		// javacardx/crypto/Cipher.getInstance(BZ)Ljavacardx/crypto/Cipher;
					putfield_a 15;		// reference thegym/thegym.aesCipher
					aload_0;
					bspush 15;
					sspush 128;
					sconst_0;
					invokestatic 42;		// javacard/security/KeyBuilder.buildKey(BSZ)Ljavacard/security/Key;
					checkcast 0 43;		// T_CLASSORINTERFACE javacard/security/AESKey
					putfield_a 16;		// reference thegym/thegym.masterKey
					aload_0;
					bspush 15;
					sspush 128;
					sconst_0;
					invokestatic 42;		// javacard/security/KeyBuilder.buildKey(BSZ)Ljavacard/security/Key;
					checkcast 0 43;		// T_CLASSORINTERFACE javacard/security/AESKey
					putfield_a 17;		// reference thegym/thegym.sessionAesKey
					aload_0;
					new 44;		// javacard/security/KeyPair
					dup;
					sconst_1;
					sspush 1024;
					invokespecial 45;		// javacard/security/KeyPair.<init>(BS)V
					putfield_a 18;		// reference thegym/thegym.rsaKeyPair
					aload_0;
					bspush 10;
					sconst_0;
					invokestatic 41;		// javacardx/crypto/Cipher.getInstance(BZ)Ljavacardx/crypto/Cipher;
					putfield_a 21;		// reference thegym/thegym.rsaCipher
					aload_0;
					bspush 10;
					sconst_0;
					invokestatic 46;		// javacard/security/Signature.getInstance(BZ)Ljavacard/security/Signature;
					putfield_a 22;		// reference thegym/thegym.rsaSignature
					aload_0;
					sconst_1;
					putfield_b 23;		// boolean thegym/thegym.cryptoInitialized
					sconst_1;
				L3:	sreturn;
				L4:	astore_1;
				L5:	aload_0;
					sconst_0;
					putfield_b 23;		// boolean thegym/thegym.cryptoInitialized
					sconst_0;
					sreturn;
			.exceptionTable {
				// start_block end_block handler_block catch_type_index
				L2 L3 L4 38;
			}
		}

		.method private deriveMasterKeyFromPIN([BSS)V {
			.stack 6;
			.locals 0;

				L0:	getfield_a_this 13;		// reference thegym/thegym.sha1
					invokevirtual 47;		// javacard/security/MessageDigest.reset()V
					getfield_a_this 13;		// reference thegym/thegym.sha1
					aload_1;
					sload_2;
					sload_3;
					invokevirtual 48;		// javacard/security/MessageDigest.update([BSS)V
					getfield_a_this 7;		// reference thegym/thegym.tempBuffer2
					sconst_0;
					sconst_1;
					bastore;
					getfield_a_this 13;		// reference thegym/thegym.sha1
					getfield_a_this 7;		// reference thegym/thegym.tempBuffer2
					sconst_0;
					sconst_1;
					getfield_a_this 12;		// reference thegym/thegym.hashBuffer
					sconst_0;
					invokevirtual 49;		// javacard/security/MessageDigest.doFinal([BSS[BS)S
					pop;
					getfield_a_this 12;		// reference thegym/thegym.hashBuffer
					sconst_0;
					getfield_a_this 8;		// reference thegym/thegym.masterKeyBuffer
					sconst_0;
					bspush 16;
					invokestatic 50;		// javacard/framework/Util.arrayCopy([BS[BSS)S
					pop;
					getfield_a_this 16;		// reference thegym/thegym.masterKey
					getfield_a_this 8;		// reference thegym/thegym.masterKeyBuffer
					sconst_0;
					invokeinterface 3 43 4;		// javacard/security/AESKey
					getfield_a_this 13;		// reference thegym/thegym.sha1
					invokevirtual 47;		// javacard/security/MessageDigest.reset()V
					getfield_a_this 13;		// reference thegym/thegym.sha1
					aload_1;
					sload_2;
					sload_3;
					invokevirtual 48;		// javacard/security/MessageDigest.update([BSS)V
					getfield_a_this 7;		// reference thegym/thegym.tempBuffer2
					sconst_0;
					sconst_2;
					bastore;
					getfield_a_this 13;		// reference thegym/thegym.sha1
					getfield_a_this 7;		// reference thegym/thegym.tempBuffer2
					sconst_0;
					sconst_1;
					getfield_a_this 12;		// reference thegym/thegym.hashBuffer
					sconst_0;
					invokevirtual 49;		// javacard/security/MessageDigest.doFinal([BSS[BS)S
					pop;
					getfield_a_this 12;		// reference thegym/thegym.hashBuffer
					sconst_0;
					getfield_a_this 9;		// reference thegym/thegym.masterIvBuffer
					sconst_0;
					bspush 16;
					invokestatic 50;		// javacard/framework/Util.arrayCopy([BS[BSS)S
					pop;
					aload_0;
					sconst_1;
					putfield_b 25;		// boolean thegym/thegym.masterKeyDerived
					getfield_a_this 12;		// reference thegym/thegym.hashBuffer
					sconst_0;
					bspush 20;
					sconst_0;
					invokestatic 51;		// javacard/framework/Util.arrayFillNonAtomic([BSSB)S
					pop;
					return;
		}

		.method public process(Ljavacard/framework/APDU;)V 7 {
			.stack 3;
			.locals 2;

			.descriptor	Ljavacard/framework/APDU;	0.10;

				L0:	aload_0;
					invokevirtual 52;		// javacard/framework/Applet.selectingApplet()Z
					ifeq L2;
				L1:	return;
				L2:	aload_1;
					invokevirtual 53;		// javacard/framework/APDU.getBuffer()[B
					astore_2;
				L3:	aload_2;
					sconst_1;
					baload;
					sstore_3;
				L4:	getfield_a_this 0;		// reference thegym/thegym.pin
					invokevirtual 54;		// javacard/framework/OwnerPIN.getTriesRemaining()B
					ifne L12;
				L5:	sload_3;
					bspush 18;
					if_scmpeq L12;
				L6:	sload_3;
					bspush 81;
					if_scmpeq L12;
				L7:	sload_3;
					bspush 50;
					if_scmpeq L12;
				L8:	sload_3;
					bspush 97;
					if_scmpeq L12;
				L9:	sload_3;
					bspush 80;
					if_scmpeq L12;
				L10:	sload_3;
					bspush 96;
					if_scmpeq L12;
				L11:	sspush 27010;
					invokestatic 55;		// javacard/framework/ISOException.throwIt(S)V
				L12:	sload_3;
					slookupswitch L41 28 -127 L36 16 L13 17 L15 18 L18 19 L14 20 L16 21 L17 32 L37 33 L38 34 L39 35 L40 36 L19 37 L20 38 L21 39 L22 48 L23 49 L24 50 L25 64 L26 80 L27 81 L28 82 L29 96 L30 97 L31 98 L32 99 L33 100 L34 101 L35;
				L13:	aload_0;
					aload_1;
					invokespecial 56;		// thegym/thegym.processVerifyPin(Ljavacard/framework/APDU;)V
					goto_w L42;
				L14:	aload_0;
					aload_1;
					invokespecial 57;		// thegym/thegym.processVerifyPinSecure(Ljavacard/framework/APDU;)V
					goto_w L42;
				L15:	aload_0;
					aload_1;
					invokespecial 58;		// thegym/thegym.processChangePin(Ljavacard/framework/APDU;)V
					goto_w L42;
				L16:	aload_0;
					aload_1;
					invokespecial 59;		// thegym/thegym.processChangePinSecure(Ljavacard/framework/APDU;)V
					goto_w L42;
				L17:	aload_0;
					aload_1;
					invokespecial 60;		// thegym/thegym.processSetRecoveryPhone(Ljavacard/framework/APDU;)V
					goto_w L42;
				L18:	aload_0;
					aload_1;
					invokespecial 61;		// thegym/thegym.processUnblockPin(Ljavacard/framework/APDU;)V
					goto_w L42;
				L19:	aload_0;
					aload_1;
					invokespecial 62;		// thegym/thegym.processUpdateInfoEncaps(Ljavacard/framework/APDU;)V
					goto_w L42;
				L20:	aload_0;
					aload_1;
					invokespecial 63;		// thegym/thegym.processGetInfoEncaps(Ljavacard/framework/APDU;)V
					goto_w L42;
				L21:	aload_0;
					aload_1;
					invokespecial 64;		// thegym/thegym.processUploadAvatarEncaps(Ljavacard/framework/APDU;)V
					goto_w L42;
				L22:	aload_0;
					aload_1;
					invokespecial 65;		// thegym/thegym.processGetAvatarEncaps(Ljavacard/framework/APDU;)V
					goto_w L42;
				L23:	aload_0;
					aload_1;
					sconst_1;
					invokespecial 66;		// thegym/thegym.processTransaction(Ljavacard/framework/APDU;Z)V
					goto_w L42;
				L24:	aload_0;
					aload_1;
					sconst_0;
					invokespecial 66;		// thegym/thegym.processTransaction(Ljavacard/framework/APDU;Z)V
					goto L42;
				L25:	aload_0;
					aload_1;
					invokespecial 67;		// thegym/thegym.processCheckBalance(Ljavacard/framework/APDU;)V
					goto L42;
				L26:	aload_0;
					aload_1;
					invokespecial 68;		// thegym/thegym.processGetHistory(Ljavacard/framework/APDU;)V
					goto L42;
				L27:	aload_0;
					aload_1;
					invokespecial 69;		// thegym/thegym.processInitCrypto(Ljavacard/framework/APDU;)V
					goto L42;
				L28:	aload_0;
					aload_1;
					invokespecial 70;		// thegym/thegym.processGetStatus(Ljavacard/framework/APDU;)V
					goto L42;
				L29:	aload_0;
					aload_1;
					invokespecial 71;		// thegym/thegym.processSetSessionKey(Ljavacard/framework/APDU;)V
					goto L42;
				L30:	aload_0;
					aload_1;
					invokespecial 72;		// thegym/thegym.processGenRSAKeyPair(Ljavacard/framework/APDU;)V
					goto L42;
				L31:	aload_0;
					aload_1;
					invokespecial 73;		// thegym/thegym.processGetRSAPublic(Ljavacard/framework/APDU;)V
					goto L42;
				L32:	aload_0;
					aload_1;
					invokespecial 74;		// thegym/thegym.processRSAEncrypt(Ljavacard/framework/APDU;)V
					goto L42;
				L33:	aload_0;
					aload_1;
					invokespecial 75;		// thegym/thegym.processRSADecrypt(Ljavacard/framework/APDU;)V
					goto L42;
				L34:	aload_0;
					aload_1;
					invokespecial 76;		// thegym/thegym.processRSASign(Ljavacard/framework/APDU;)V
					goto L42;
				L35:	aload_0;
					aload_1;
					invokespecial 77;		// thegym/thegym.processRSAVerify(Ljavacard/framework/APDU;)V
					goto L42;
				L36:	aload_0;
					aload_1;
					invokespecial 78;		// thegym/thegym.processHashData(Ljavacard/framework/APDU;)V
					goto L42;
				L37:	aload_0;
					aload_1;
					invokespecial 79;		// thegym/thegym.processUpdateInfoLegacy(Ljavacard/framework/APDU;)V
					goto L42;
				L38:	aload_0;
					aload_1;
					invokespecial 80;		// thegym/thegym.processGetInfoLegacy(Ljavacard/framework/APDU;)V
					goto L42;
				L39:	aload_0;
					aload_1;
					invokespecial 81;		// thegym/thegym.processUploadAvatarLegacy(Ljavacard/framework/APDU;)V
					goto L42;
				L40:	aload_0;
					aload_1;
					invokespecial 82;		// thegym/thegym.processGetAvatarLegacy(Ljavacard/framework/APDU;)V
					goto L42;
				L41:	sspush 27904;
					invokestatic 55;		// javacard/framework/ISOException.throwIt(S)V
				L42:	return;
		}

		.method private processGetStatus(Ljavacard/framework/APDU;)V {
			.stack 3;
			.locals 1;

			.descriptor	Ljavacard/framework/APDU;	0.10;

				L0:	aload_1;
					invokevirtual 53;		// javacard/framework/APDU.getBuffer()[B
					astore_2;
				L1:	aload_2;
					sconst_0;
					getfield_b_this 23;		// boolean thegym/thegym.cryptoInitialized
					ifeq L3;
				L2:	sconst_1;
					goto L4;
				L3:	sconst_0;
				L4:	bastore;
					aload_2;
					sconst_1;
					getfield_b_this 24;		// boolean thegym/thegym.rsaKeysGenerated
					ifeq L6;
				L5:	sconst_1;
					goto L7;
				L6:	sconst_0;
				L7:	bastore;
					aload_2;
					sconst_2;
					getfield_b_this 25;		// boolean thegym/thegym.masterKeyDerived
					ifeq L9;
				L8:	sconst_1;
					goto L10;
				L9:	sconst_0;
				L10:	bastore;
					aload_2;
					sconst_3;
					getfield_a_this 0;		// reference thegym/thegym.pin
					invokevirtual 83;		// javacard/framework/OwnerPIN.isValidated()Z
					ifeq L12;
				L11:	sconst_1;
					goto L13;
				L12:	sconst_0;
				L13:	bastore;
					aload_2;
					sconst_4;
					getfield_a_this 0;		// reference thegym/thegym.pin
					invokevirtual 54;		// javacard/framework/OwnerPIN.getTriesRemaining()B
					bastore;
					aload_2;
					sconst_5;
					sconst_2;
					bastore;
					aload_1;
					sconst_0;
					bspush 6;
					invokevirtual 84;		// javacard/framework/APDU.setOutgoingAndSend(SS)V
					return;
		}

		.method private processSetSessionKey(Ljavacard/framework/APDU;)V {
			.stack 3;
			.locals 2;

			.descriptor	Ljavacard/framework/APDU;	0.10;

				L0:	getfield_b_this 24;		// boolean thegym/thegym.rsaKeysGenerated
					ifne L2;
				L1:	sspush 27013;
					invokestatic 55;		// javacard/framework/ISOException.throwIt(S)V
				L2:	aload_1;
					invokevirtual 53;		// javacard/framework/APDU.getBuffer()[B
					astore_2;
				L3:	aload_1;
					invokevirtual 85;		// javacard/framework/APDU.setIncomingAndReceive()S
					sstore_3;
				L4:	sload_3;
					sspush 128;
					if_scmpeq L6;
				L5:	sspush 26368;
					invokestatic 55;		// javacard/framework/ISOException.throwIt(S)V
				L6:	aload_0;
					aload_2;
					sconst_5;
					invokespecial 86;		// thegym/thegym.decapsulateSessionKey([BS)Z
					ifne L8;
				L7:	sspush 27012;
					invokestatic 55;		// javacard/framework/ISOException.throwIt(S)V
				L8:	return;
		}

		.method private processInitCrypto(Ljavacard/framework/APDU;)V {
			.stack 3;
			.locals 1;

			.descriptor	Ljavacard/framework/APDU;	0.10;

				L0:	aload_1;
					invokevirtual 53;		// javacard/framework/APDU.getBuffer()[B
					astore_2;
				L1:	aload_2;
					sconst_0;
					aload_0;
					invokespecial 87;		// thegym/thegym.initCrypto()Z
					ifeq L3;
				L2:	sconst_1;
					goto L4;
				L3:	sconst_0;
				L4:	bastore;
					aload_1;
					sconst_0;
					sconst_1;
					invokevirtual 84;		// javacard/framework/APDU.setOutgoingAndSend(SS)V
					return;
		}

		.method private processVerifyPin(Ljavacard/framework/APDU;)V {
			.stack 5;
			.locals 3;

			.descriptor	Ljavacard/framework/APDU;	0.10;

				L0:	aload_1;
					invokevirtual 53;		// javacard/framework/APDU.getBuffer()[B
					astore_2;
				L1:	aload_1;
					invokevirtual 85;		// javacard/framework/APDU.setIncomingAndReceive()S
					sstore_3;
				L2:	sload_3;
					bspush 6;
					if_scmpeq L4;
				L3:	sspush 26368;
					invokestatic 55;		// javacard/framework/ISOException.throwIt(S)V
				L4:	aload_2;
					sconst_5;
					getfield_a_this 1;		// reference thegym/thegym.pinBuffer
					sconst_0;
					bspush 6;
					invokestatic 50;		// javacard/framework/Util.arrayCopy([BS[BSS)S
					pop;
					getfield_a_this 0;		// reference thegym/thegym.pin
					aload_2;
					sconst_5;
					sload_3;
					s2b;
					invokevirtual 88;		// javacard/framework/OwnerPIN.check([BSB)Z
					ifne L7;
				L5:	getfield_a_this 1;		// reference thegym/thegym.pinBuffer
					sconst_0;
					bspush 6;
					sconst_0;
					invokestatic 51;		// javacard/framework/Util.arrayFillNonAtomic([BSSB)S
					pop;
					getfield_a_this 0;		// reference thegym/thegym.pin
					invokevirtual 54;		// javacard/framework/OwnerPIN.getTriesRemaining()B
					sstore 4;
				L6:	sspush 25536;
					sload 4;
					sadd;
					invokestatic 55;		// javacard/framework/ISOException.throwIt(S)V
				L7:	getfield_b_this 23;		// boolean thegym/thegym.cryptoInitialized
					ifne L9;
				L8:	aload_0;
					invokespecial 87;		// thegym/thegym.initCrypto()Z
					pop;
				L9:	aload_0;
					getfield_a_this 1;		// reference thegym/thegym.pinBuffer
					sconst_0;
					bspush 6;
					invokespecial 89;		// thegym/thegym.deriveMasterKeyFromPIN([BSS)V
					getfield_a_this 1;		// reference thegym/thegym.pinBuffer
					sconst_0;
					bspush 6;
					sconst_0;
					invokestatic 51;		// javacard/framework/Util.arrayFillNonAtomic([BSSB)S
					pop;
					return;
		}

		.method private processVerifyPinSecure(Ljavacard/framework/APDU;)V {
			.stack 6;
			.locals 4;

			.descriptor	Ljavacard/framework/APDU;	0.10;

				L0:	getfield_b_this 24;		// boolean thegym/thegym.rsaKeysGenerated
					ifne L2;
				L1:	sspush 27013;
					invokestatic 55;		// javacard/framework/ISOException.throwIt(S)V
				L2:	aload_1;
					invokevirtual 53;		// javacard/framework/APDU.getBuffer()[B
					astore_2;
				L3:	aload_1;
					invokevirtual 85;		// javacard/framework/APDU.setIncomingAndReceive()S
					sstore_3;
				L4:	sload_3;
					sspush 128;
					if_scmpeq L6;
				L5:	sspush 26368;
					invokestatic 55;		// javacard/framework/ISOException.throwIt(S)V
				L6:	getfield_a_this 21;		// reference thegym/thegym.rsaCipher
					getfield_a_this 20;		// reference thegym/thegym.rsaPrivateKey
					sconst_1;
					invokevirtual 90;		// javacardx/crypto/Cipher.init(Ljavacard/security/Key;B)V
					getfield_a_this 21;		// reference thegym/thegym.rsaCipher
					aload_2;
					sconst_5;
					sspush 128;
					getfield_a_this 6;		// reference thegym/thegym.tempBuffer
					sconst_0;
					invokevirtual 91;		// javacardx/crypto/Cipher.doFinal([BSS[BS)S
					sstore 4;
				L7:	sload 4;
					bspush 6;
					if_scmpeq L9;
				L8:	sspush 27264;
					invokestatic 55;		// javacard/framework/ISOException.throwIt(S)V
				L9:	getfield_a_this 6;		// reference thegym/thegym.tempBuffer
					sconst_0;
					getfield_a_this 1;		// reference thegym/thegym.pinBuffer
					sconst_0;
					bspush 6;
					invokestatic 50;		// javacard/framework/Util.arrayCopy([BS[BSS)S
					pop;
					getfield_a_this 0;		// reference thegym/thegym.pin
					getfield_a_this 6;		// reference thegym/thegym.tempBuffer
					sconst_0;
					bspush 6;
					invokevirtual 88;		// javacard/framework/OwnerPIN.check([BSB)Z
					ifne L12;
				L10:	getfield_a_this 1;		// reference thegym/thegym.pinBuffer
					sconst_0;
					bspush 6;
					sconst_0;
					invokestatic 51;		// javacard/framework/Util.arrayFillNonAtomic([BSSB)S
					pop;
					getfield_a_this 6;		// reference thegym/thegym.tempBuffer
					sconst_0;
					sload 4;
					sconst_0;
					invokestatic 51;		// javacard/framework/Util.arrayFillNonAtomic([BSSB)S
					pop;
					getfield_a_this 0;		// reference thegym/thegym.pin
					invokevirtual 54;		// javacard/framework/OwnerPIN.getTriesRemaining()B
					sstore 5;
				L11:	sspush 25536;
					sload 5;
					sadd;
					invokestatic 55;		// javacard/framework/ISOException.throwIt(S)V
				L12:	getfield_b_this 23;		// boolean thegym/thegym.cryptoInitialized
					ifne L14;
				L13:	aload_0;
					invokespecial 87;		// thegym/thegym.initCrypto()Z
					pop;
				L14:	aload_0;
					getfield_a_this 1;		// reference thegym/thegym.pinBuffer
					sconst_0;
					bspush 6;
					invokespecial 89;		// thegym/thegym.deriveMasterKeyFromPIN([BSS)V
					getfield_a_this 1;		// reference thegym/thegym.pinBuffer
					sconst_0;
					bspush 6;
					sconst_0;
					invokestatic 51;		// javacard/framework/Util.arrayFillNonAtomic([BSSB)S
					pop;
					getfield_a_this 6;		// reference thegym/thegym.tempBuffer
					sconst_0;
					sload 4;
					sconst_0;
					invokestatic 51;		// javacard/framework/Util.arrayFillNonAtomic([BSSB)S
					pop;
					aload_2;
					sconst_0;
					sconst_1;
					bastore;
					aload_1;
					sconst_0;
					sconst_1;
					invokevirtual 84;		// javacard/framework/APDU.setOutgoingAndSend(SS)V
					return;
		}

		.method private processChangePin(Ljavacard/framework/APDU;)V {
			.stack 4;
			.locals 3;

			.descriptor	Ljavacard/framework/APDU;	0.10;

				L0:	getfield_a_this 0;		// reference thegym/thegym.pin
					invokevirtual 83;		// javacard/framework/OwnerPIN.isValidated()Z
					ifne L2;
				L1:	sspush 27010;
					invokestatic 55;		// javacard/framework/ISOException.throwIt(S)V
				L2:	aload_1;
					invokevirtual 53;		// javacard/framework/APDU.getBuffer()[B
					astore_2;
				L3:	aload_1;
					invokevirtual 85;		// javacard/framework/APDU.setIncomingAndReceive()S
					sstore_3;
				L4:	sload_3;
					bspush 12;
					if_scmpeq L6;
				L5:	sspush 26368;
					invokestatic 55;		// javacard/framework/ISOException.throwIt(S)V
				L6:	getfield_a_this 0;		// reference thegym/thegym.pin
					aload_2;
					sconst_5;
					bspush 6;
					invokevirtual 88;		// javacard/framework/OwnerPIN.check([BSB)Z
					ifne L9;
				L7:	getfield_a_this 0;		// reference thegym/thegym.pin
					invokevirtual 54;		// javacard/framework/OwnerPIN.getTriesRemaining()B
					sstore 4;
				L8:	sspush 25536;
					sload 4;
					sadd;
					invokestatic 55;		// javacard/framework/ISOException.throwIt(S)V
				L9:	getfield_a_this 0;		// reference thegym/thegym.pin
					aload_2;
					bspush 11;
					bspush 6;
					invokevirtual 35;		// javacard/framework/OwnerPIN.update([BSB)V
					aload_0;
					aload_2;
					bspush 11;
					bspush 6;
					invokespecial 89;		// thegym/thegym.deriveMasterKeyFromPIN([BSS)V
					return;
		}

		.method private processChangePinSecure(Ljavacard/framework/APDU;)V {
			.stack 6;
			.locals 6;

			.descriptor	Ljavacard/framework/APDU;	0.10;

				L0:	getfield_a_this 0;		// reference thegym/thegym.pin
					invokevirtual 83;		// javacard/framework/OwnerPIN.isValidated()Z
					ifne L2;
				L1:	sspush 27010;
					invokestatic 55;		// javacard/framework/ISOException.throwIt(S)V
				L2:	getfield_b_this 24;		// boolean thegym/thegym.rsaKeysGenerated
					ifne L4;
				L3:	sspush 27013;
					invokestatic 55;		// javacard/framework/ISOException.throwIt(S)V
				L4:	aload_1;
					invokevirtual 53;		// javacard/framework/APDU.getBuffer()[B
					astore_2;
				L5:	aload_1;
					invokevirtual 85;		// javacard/framework/APDU.setIncomingAndReceive()S
					sstore_3;
				L6:	sload_3;
					sspush 128;
					if_scmpeq L8;
				L7:	sspush 26368;
					invokestatic 55;		// javacard/framework/ISOException.throwIt(S)V
				L8:	getfield_a_this 21;		// reference thegym/thegym.rsaCipher
					getfield_a_this 20;		// reference thegym/thegym.rsaPrivateKey
					sconst_1;
					invokevirtual 90;		// javacardx/crypto/Cipher.init(Ljavacard/security/Key;B)V
					getfield_a_this 21;		// reference thegym/thegym.rsaCipher
					aload_2;
					sconst_5;
					sspush 128;
					getfield_a_this 6;		// reference thegym/thegym.tempBuffer
					sconst_0;
					invokevirtual 91;		// javacardx/crypto/Cipher.doFinal([BSS[BS)S
					sstore 4;
				L9:	sload 4;
					bspush 12;
					if_scmpeq L11;
				L10:	getfield_a_this 6;		// reference thegym/thegym.tempBuffer
					sconst_0;
					sload 4;
					sconst_0;
					invokestatic 51;		// javacard/framework/Util.arrayFillNonAtomic([BSSB)S
					pop;
					sspush 27264;
					invokestatic 55;		// javacard/framework/ISOException.throwIt(S)V
				L11:	getfield_a_this 0;		// reference thegym/thegym.pin
					getfield_a_this 6;		// reference thegym/thegym.tempBuffer
					sconst_0;
					bspush 6;
					invokevirtual 88;		// javacard/framework/OwnerPIN.check([BSB)Z
					ifne L14;
				L12:	getfield_a_this 6;		// reference thegym/thegym.tempBuffer
					sconst_0;
					sload 4;
					sconst_0;
					invokestatic 51;		// javacard/framework/Util.arrayFillNonAtomic([BSSB)S
					pop;
					getfield_a_this 0;		// reference thegym/thegym.pin
					invokevirtual 54;		// javacard/framework/OwnerPIN.getTriesRemaining()B
					sstore 5;
				L13:	sspush 25536;
					sload 5;
					sadd;
					invokestatic 55;		// javacard/framework/ISOException.throwIt(S)V
				L14:	bspush 16;
					sconst_2;
					invokestatic 92;		// javacard/framework/JCSystem.makeTransientByteArray(SB)[B
					astore 5;
				L15:	bspush 16;
					sconst_2;
					invokestatic 92;		// javacard/framework/JCSystem.makeTransientByteArray(SB)[B
					astore 6;
				L16:	getfield_a_this 8;		// reference thegym/thegym.masterKeyBuffer
					sconst_0;
					aload 5;
					sconst_0;
					bspush 16;
					invokestatic 50;		// javacard/framework/Util.arrayCopy([BS[BSS)S
					pop;
					getfield_a_this 9;		// reference thegym/thegym.masterIvBuffer
					sconst_0;
					aload 6;
					sconst_0;
					bspush 16;
					invokestatic 50;		// javacard/framework/Util.arrayCopy([BS[BSS)S
					pop;
					bspush 14;
					sspush 128;
					sconst_0;
					invokestatic 42;		// javacard/security/KeyBuilder.buildKey(BSZ)Ljavacard/security/Key;
					checkcast 0 43;		// T_CLASSORINTERFACE javacard/security/AESKey
					astore 7;
				L17:	aload 7;
					aload 5;
					sconst_0;
					invokeinterface 3 43 4;		// javacard/security/AESKey
					getfield_a_this 0;		// reference thegym/thegym.pin
					getfield_a_this 6;		// reference thegym/thegym.tempBuffer
					bspush 6;
					bspush 6;
					invokevirtual 35;		// javacard/framework/OwnerPIN.update([BSB)V
					aload_0;
					getfield_a_this 6;		// reference thegym/thegym.tempBuffer
					bspush 6;
					bspush 6;
					invokespecial 89;		// thegym/thegym.deriveMasterKeyFromPIN([BSS)V
					getfield_s_this 26;		// short thegym/thegym.userDataLen
					ifle L19;
				L18:	aload_0;
					getfield_a_this 2;		// reference thegym/thegym.userData
					getfield_s_this 26;		// short thegym/thegym.userDataLen
					aload 7;
					aload 6;
					invokespecial 93;		// thegym/thegym.reEncryptData([BSLjavacard/security/AESKey;[B)V
				L19:	getfield_s_this 27;		// short thegym/thegym.avatarCurrentSize
					ifle L21;
				L20:	aload_0;
					aload 7;
					aload 6;
					invokespecial 94;		// thegym/thegym.reEncryptAvatar(Ljavacard/security/AESKey;[B)V
				L21:	getfield_a_this 6;		// reference thegym/thegym.tempBuffer
					sconst_0;
					sload 4;
					sconst_0;
					invokestatic 51;		// javacard/framework/Util.arrayFillNonAtomic([BSSB)S
					pop;
					aload 5;
					sconst_0;
					bspush 16;
					sconst_0;
					invokestatic 51;		// javacard/framework/Util.arrayFillNonAtomic([BSSB)S
					pop;
					aload 6;
					sconst_0;
					bspush 16;
					sconst_0;
					invokestatic 51;		// javacard/framework/Util.arrayFillNonAtomic([BSSB)S
					pop;
					aload_2;
					sconst_0;
					sconst_1;
					bastore;
					aload_1;
					sconst_0;
					sconst_1;
					invokevirtual 84;		// javacard/framework/APDU.setOutgoingAndSend(SS)V
					return;
		}

		.method private processSetRecoveryPhone(Ljavacard/framework/APDU;)V {
			.stack 5;
			.locals 2;

			.descriptor	Ljavacard/framework/APDU;	0.10;

				L0:	aload_1;
					invokevirtual 53;		// javacard/framework/APDU.getBuffer()[B
					astore_2;
				L1:	aload_1;
					invokevirtual 85;		// javacard/framework/APDU.setIncomingAndReceive()S
					sstore_3;
				L2:	sload_3;
					bspush 10;
					if_scmplt L4;
				L3:	sload_3;
					bspush 12;
					if_scmple L5;
				L4:	sspush 26368;
					invokestatic 55;		// javacard/framework/ISOException.throwIt(S)V
				L5:	aload_2;
					sconst_5;
					getfield_a_this 4;		// reference thegym/thegym.recoverySDT
					sconst_0;
					sload_3;
					invokestatic 50;		// javacard/framework/Util.arrayCopy([BS[BSS)S
					pop;
					aload_0;
					sload_3;
					s2b;
					putfield_b 28;		// byte thegym/thegym.recoverySDTLen
					return;
		}

		.method private reEncryptData([BSLjavacard/security/AESKey;[B)V {
			.stack 6;
			.locals 5;

			.descriptor	Ljavacard/security/AESKey;	1.20;

				L0:	getfield_a_this 15;		// reference thegym/thegym.aesCipher
					aload_3;
					sconst_1;
					aload 4;
					sconst_0;
					bspush 16;
					invokevirtual 95;		// javacardx/crypto/Cipher.init(Ljavacard/security/Key;B[BSS)V
					getfield_a_this 15;		// reference thegym/thegym.aesCipher
					aload_1;
					sconst_0;
					sload_2;
					getfield_a_this 6;		// reference thegym/thegym.tempBuffer
					sconst_0;
					invokevirtual 91;		// javacardx/crypto/Cipher.doFinal([BSS[BS)S
					sstore 5;
				L1:	getfield_a_this 6;		// reference thegym/thegym.tempBuffer
					sload 5;
					sconst_1;
					ssub;
					baload;
					sstore 6;
				L2:	sload 6;
					ifle L5;
				L3:	sload 6;
					bspush 16;
					if_scmpgt L5;
				L4:	sload 5;
					sload 6;
					ssub;
					sstore 5;
				L5:	sload 5;
					s2i;
					bipush 16;
					iadd;
					bipush 16;
					idiv;
					bipush 16;
					imul;
					i2s;
					sstore 7;
				L6:	sload 7;
					sload 5;
					ssub;
					s2b;
					sstore 8;
				L7:	sload 5;
					sstore 9;
				L8:	sload 9;
					sload 7;
					if_scmpge L10;
				L9:	getfield_a_this 6;		// reference thegym/thegym.tempBuffer
					sload 9;
					sload 8;
					bastore;
					sinc 9 1;
					goto L8;
				L10:	getfield_a_this 15;		// reference thegym/thegym.aesCipher
					getfield_a_this 16;		// reference thegym/thegym.masterKey
					sconst_2;
					getfield_a_this 9;		// reference thegym/thegym.masterIvBuffer
					sconst_0;
					bspush 16;
					invokevirtual 95;		// javacardx/crypto/Cipher.init(Ljavacard/security/Key;B[BSS)V
					getfield_a_this 15;		// reference thegym/thegym.aesCipher
					getfield_a_this 6;		// reference thegym/thegym.tempBuffer
					sconst_0;
					sload 7;
					aload_1;
					sconst_0;
					invokevirtual 91;		// javacardx/crypto/Cipher.doFinal([BSS[BS)S
					sstore 9;
				L11:	return;
		}

		.method private reEncryptAvatar(Ljavacard/security/AESKey;[B)V {
			.stack 6;
			.locals 5;

			.descriptor	Ljavacard/security/AESKey;	1.20;

				L0:	getfield_a_this 15;		// reference thegym/thegym.aesCipher
					aload_1;
					sconst_1;
					aload_2;
					sconst_0;
					bspush 16;
					invokevirtual 95;		// javacardx/crypto/Cipher.init(Ljavacard/security/Key;B[BSS)V
					getfield_a_this 15;		// reference thegym/thegym.aesCipher
					getfield_a_this 3;		// reference thegym/thegym.avatarData
					sconst_0;
					getfield_s_this 27;		// short thegym/thegym.avatarCurrentSize
					getfield_a_this 6;		// reference thegym/thegym.tempBuffer
					sconst_0;
					invokevirtual 91;		// javacardx/crypto/Cipher.doFinal([BSS[BS)S
					sstore_3;
				L1:	getfield_a_this 6;		// reference thegym/thegym.tempBuffer
					sload_3;
					sconst_1;
					ssub;
					baload;
					sstore 4;
				L2:	sload 4;
					ifle L5;
				L3:	sload 4;
					bspush 16;
					if_scmpgt L5;
				L4:	sload_3;
					sload 4;
					ssub;
					sstore_3;
				L5:	sload_3;
					s2i;
					bipush 16;
					iadd;
					bipush 16;
					idiv;
					bipush 16;
					imul;
					i2s;
					sstore 5;
				L6:	sload 5;
					sload_3;
					ssub;
					s2b;
					sstore 6;
				L7:	sload_3;
					sstore 7;
				L8:	sload 7;
					sload 5;
					if_scmpge L10;
				L9:	getfield_a_this 6;		// reference thegym/thegym.tempBuffer
					sload 7;
					sload 6;
					bastore;
					sinc 7 1;
					goto L8;
				L10:	getfield_a_this 15;		// reference thegym/thegym.aesCipher
					getfield_a_this 16;		// reference thegym/thegym.masterKey
					sconst_2;
					getfield_a_this 9;		// reference thegym/thegym.masterIvBuffer
					sconst_0;
					bspush 16;
					invokevirtual 95;		// javacardx/crypto/Cipher.init(Ljavacard/security/Key;B[BSS)V
					getfield_a_this 15;		// reference thegym/thegym.aesCipher
					getfield_a_this 6;		// reference thegym/thegym.tempBuffer
					sconst_0;
					sload 5;
					getfield_a_this 3;		// reference thegym/thegym.avatarData
					sconst_0;
					invokevirtual 91;		// javacardx/crypto/Cipher.doFinal([BSS[BS)S
					sstore 7;
				L11:	aload_0;
					sload 7;
					putfield_s 27;		// short thegym/thegym.avatarCurrentSize
					return;
		}

		.method private processUnblockPin(Ljavacard/framework/APDU;)V {
			.stack 5;
			.locals 3;

			.descriptor	Ljavacard/framework/APDU;	0.10;

				L0:	aload_1;
					invokevirtual 53;		// javacard/framework/APDU.getBuffer()[B
					astore_2;
				L1:	aload_1;
					invokevirtual 85;		// javacard/framework/APDU.setIncomingAndReceive()S
					sstore_3;
				L2:	getfield_b_this 28;		// byte thegym/thegym.recoverySDTLen
					ifne L4;
				L3:	sspush 27013;
					invokestatic 55;		// javacard/framework/ISOException.throwIt(S)V
				L4:	sload_3;
					getfield_b_this 28;		// byte thegym/thegym.recoverySDTLen
					if_scmpeq L6;
				L5:	sspush 27264;
					invokestatic 55;		// javacard/framework/ISOException.throwIt(S)V
				L6:	aload_2;
					sconst_5;
					getfield_a_this 4;		// reference thegym/thegym.recoverySDT
					sconst_0;
					sload_3;
					invokestatic 96;		// javacard/framework/Util.arrayCompare([BS[BSS)B
					ifeq L8;
				L7:	sspush 27264;
					invokestatic 55;		// javacard/framework/ISOException.throwIt(S)V
				L8:	getfield_a_this 0;		// reference thegym/thegym.pin
					invokevirtual 97;		// javacard/framework/OwnerPIN.resetAndUnblock()V
					bspush 6;
					newarray 11;
					dup;
					sconst_0;
					bspush 49;
					bastore;
					dup;
					sconst_1;
					bspush 50;
					bastore;
					dup;
					sconst_2;
					bspush 51;
					bastore;
					dup;
					sconst_3;
					bspush 52;
					bastore;
					dup;
					sconst_4;
					bspush 53;
					bastore;
					dup;
					sconst_5;
					bspush 54;
					bastore;
					astore 4;
				L9:	getfield_a_this 0;		// reference thegym/thegym.pin
					aload 4;
					sconst_0;
					bspush 6;
					invokevirtual 35;		// javacard/framework/OwnerPIN.update([BSB)V
					aload_0;
					sconst_0;
					putfield_b 25;		// boolean thegym/thegym.masterKeyDerived
					getfield_a_this 8;		// reference thegym/thegym.masterKeyBuffer
					sconst_0;
					bspush 16;
					sconst_0;
					invokestatic 51;		// javacard/framework/Util.arrayFillNonAtomic([BSSB)S
					pop;
					getfield_a_this 9;		// reference thegym/thegym.masterIvBuffer
					sconst_0;
					bspush 16;
					sconst_0;
					invokestatic 51;		// javacard/framework/Util.arrayFillNonAtomic([BSSB)S
					pop;
					return;
		}

		.method private processGenRSAKeyPair(Ljavacard/framework/APDU;)V {
			.stack 3;
			.locals 1;

			.descriptor	Ljavacard/framework/APDU;	0.10;

				L0:	getfield_b_this 23;		// boolean thegym/thegym.cryptoInitialized
					ifne L3;
				L1:	aload_0;
					invokespecial 87;		// thegym/thegym.initCrypto()Z
					ifne L3;
				L2:	sspush 27013;
					invokestatic 55;		// javacard/framework/ISOException.throwIt(S)V
				L3:	getfield_a_this 18;		// reference thegym/thegym.rsaKeyPair
					invokevirtual 98;		// javacard/security/KeyPair.genKeyPair()V
					aload_0;
					getfield_a_this 18;		// reference thegym/thegym.rsaKeyPair
					invokevirtual 99;		// javacard/security/KeyPair.getPublic()Ljavacard/security/PublicKey;
					checkcast 0 100;		// T_CLASSORINTERFACE javacard/security/RSAPublicKey
					putfield_a 19;		// reference thegym/thegym.rsaPublicKey
					aload_0;
					getfield_a_this 18;		// reference thegym/thegym.rsaKeyPair
					invokevirtual 101;		// javacard/security/KeyPair.getPrivate()Ljavacard/security/PrivateKey;
					checkcast 0 102;		// T_CLASSORINTERFACE javacard/security/RSAPrivateKey
					putfield_a 20;		// reference thegym/thegym.rsaPrivateKey
					aload_0;
					sconst_1;
					putfield_b 24;		// boolean thegym/thegym.rsaKeysGenerated
					aload_1;
					invokevirtual 53;		// javacard/framework/APDU.getBuffer()[B
					astore_2;
				L4:	aload_2;
					sconst_0;
					sconst_1;
					bastore;
					aload_1;
					sconst_0;
					sconst_1;
					invokevirtual 84;		// javacard/framework/APDU.setOutgoingAndSend(SS)V
				L5:	goto L8;
				L6:	astore_2;
				L7:	sspush 27013;
					invokestatic 55;		// javacard/framework/ISOException.throwIt(S)V
				L8:	return;
			.exceptionTable {
				// start_block end_block handler_block catch_type_index
				L3 L5 L6 38;
			}
		}

		.method private processGetRSAPublic(Ljavacard/framework/APDU;)V {
			.stack 3;
			.locals 3;

			.descriptor	Ljavacard/framework/APDU;	0.10;

				L0:	getfield_b_this 24;		// boolean thegym/thegym.rsaKeysGenerated
					ifne L2;
				L1:	sspush 27013;
					invokestatic 55;		// javacard/framework/ISOException.throwIt(S)V
				L2:	aload_1;
					invokevirtual 53;		// javacard/framework/APDU.getBuffer()[B
					astore_2;
				L3:	aload_2;
					sconst_2;
					baload;
					sstore_3;
				L4:	sconst_0;
					sstore 4;
				L5:	sload_3;
					sconst_1;
					if_scmpne L7;
				L6:	getfield_a_this 19;		// reference thegym/thegym.rsaPublicKey
					aload_2;
					sconst_0;
					invokeinterface 3 100 5;		// javacard/security/RSAPublicKey
					sstore 4;
					goto L10;
				L7:	sload_3;
					sconst_2;
					if_scmpne L9;
				L8:	getfield_a_this 19;		// reference thegym/thegym.rsaPublicKey
					aload_2;
					sconst_0;
					invokeinterface 3 100 4;		// javacard/security/RSAPublicKey
					sstore 4;
					goto L10;
				L9:	sspush 27270;
					invokestatic 55;		// javacard/framework/ISOException.throwIt(S)V
				L10:	aload_1;
					sconst_0;
					sload 4;
					invokevirtual 84;		// javacard/framework/APDU.setOutgoingAndSend(SS)V
					return;
		}

		.method private processRSAEncrypt(Ljavacard/framework/APDU;)V {
			.stack 6;
			.locals 3;

			.descriptor	Ljavacard/framework/APDU;	0.10;

				L0:	getfield_b_this 24;		// boolean thegym/thegym.rsaKeysGenerated
					ifne L2;
				L1:	sspush 27013;
					invokestatic 55;		// javacard/framework/ISOException.throwIt(S)V
				L2:	aload_1;
					invokevirtual 53;		// javacard/framework/APDU.getBuffer()[B
					astore_2;
				L3:	aload_1;
					invokevirtual 85;		// javacard/framework/APDU.setIncomingAndReceive()S
					sstore_3;
				L4:	getfield_a_this 21;		// reference thegym/thegym.rsaCipher
					getfield_a_this 19;		// reference thegym/thegym.rsaPublicKey
					sconst_2;
					invokevirtual 90;		// javacardx/crypto/Cipher.init(Ljavacard/security/Key;B)V
					getfield_a_this 21;		// reference thegym/thegym.rsaCipher
					aload_2;
					sconst_5;
					sload_3;
					getfield_a_this 6;		// reference thegym/thegym.tempBuffer
					sconst_0;
					invokevirtual 91;		// javacardx/crypto/Cipher.doFinal([BSS[BS)S
					sstore 4;
				L5:	getfield_a_this 6;		// reference thegym/thegym.tempBuffer
					sconst_0;
					aload_2;
					sconst_0;
					sload 4;
					invokestatic 50;		// javacard/framework/Util.arrayCopy([BS[BSS)S
					pop;
					aload_1;
					sconst_0;
					sload 4;
					invokevirtual 84;		// javacard/framework/APDU.setOutgoingAndSend(SS)V
					return;
		}

		.method private processRSADecrypt(Ljavacard/framework/APDU;)V {
			.stack 6;
			.locals 3;

			.descriptor	Ljavacard/framework/APDU;	0.10;

				L0:	getfield_a_this 0;		// reference thegym/thegym.pin
					invokevirtual 83;		// javacard/framework/OwnerPIN.isValidated()Z
					ifne L2;
				L1:	sspush 27010;
					invokestatic 55;		// javacard/framework/ISOException.throwIt(S)V
				L2:	getfield_b_this 24;		// boolean thegym/thegym.rsaKeysGenerated
					ifne L4;
				L3:	sspush 27013;
					invokestatic 55;		// javacard/framework/ISOException.throwIt(S)V
				L4:	aload_1;
					invokevirtual 53;		// javacard/framework/APDU.getBuffer()[B
					astore_2;
				L5:	aload_1;
					invokevirtual 85;		// javacard/framework/APDU.setIncomingAndReceive()S
					sstore_3;
				L6:	getfield_a_this 21;		// reference thegym/thegym.rsaCipher
					getfield_a_this 20;		// reference thegym/thegym.rsaPrivateKey
					sconst_1;
					invokevirtual 90;		// javacardx/crypto/Cipher.init(Ljavacard/security/Key;B)V
					getfield_a_this 21;		// reference thegym/thegym.rsaCipher
					aload_2;
					sconst_5;
					sload_3;
					getfield_a_this 6;		// reference thegym/thegym.tempBuffer
					sconst_0;
					invokevirtual 91;		// javacardx/crypto/Cipher.doFinal([BSS[BS)S
					sstore 4;
				L7:	getfield_a_this 6;		// reference thegym/thegym.tempBuffer
					sconst_0;
					aload_2;
					sconst_0;
					sload 4;
					invokestatic 50;		// javacard/framework/Util.arrayCopy([BS[BSS)S
					pop;
					aload_1;
					sconst_0;
					sload 4;
					invokevirtual 84;		// javacard/framework/APDU.setOutgoingAndSend(SS)V
					return;
		}

		.method private processRSASign(Ljavacard/framework/APDU;)V {
			.stack 6;
			.locals 3;

			.descriptor	Ljavacard/framework/APDU;	0.10;

				L0:	getfield_a_this 0;		// reference thegym/thegym.pin
					invokevirtual 83;		// javacard/framework/OwnerPIN.isValidated()Z
					ifne L2;
				L1:	sspush 27010;
					invokestatic 55;		// javacard/framework/ISOException.throwIt(S)V
				L2:	getfield_b_this 24;		// boolean thegym/thegym.rsaKeysGenerated
					ifne L4;
				L3:	sspush 27013;
					invokestatic 55;		// javacard/framework/ISOException.throwIt(S)V
				L4:	aload_1;
					invokevirtual 53;		// javacard/framework/APDU.getBuffer()[B
					astore_2;
				L5:	aload_1;
					invokevirtual 85;		// javacard/framework/APDU.setIncomingAndReceive()S
					sstore_3;
				L6:	getfield_a_this 22;		// reference thegym/thegym.rsaSignature
					getfield_a_this 20;		// reference thegym/thegym.rsaPrivateKey
					sconst_1;
					invokevirtual 103;		// javacard/security/Signature.init(Ljavacard/security/Key;B)V
					getfield_a_this 22;		// reference thegym/thegym.rsaSignature
					aload_2;
					sconst_5;
					sload_3;
					getfield_a_this 6;		// reference thegym/thegym.tempBuffer
					sconst_0;
					invokevirtual 104;		// javacard/security/Signature.sign([BSS[BS)S
					sstore 4;
				L7:	getfield_a_this 6;		// reference thegym/thegym.tempBuffer
					sconst_0;
					aload_2;
					sconst_0;
					sload 4;
					invokestatic 50;		// javacard/framework/Util.arrayCopy([BS[BSS)S
					pop;
					aload_1;
					sconst_0;
					sload 4;
					invokevirtual 84;		// javacard/framework/APDU.setOutgoingAndSend(SS)V
					return;
		}

		.method private processRSAVerify(Ljavacard/framework/APDU;)V {
			.stack 7;
			.locals 6;

			.descriptor	Ljavacard/framework/APDU;	0.10;

				L0:	getfield_b_this 24;		// boolean thegym/thegym.rsaKeysGenerated
					ifne L2;
				L1:	sspush 27013;
					invokestatic 55;		// javacard/framework/ISOException.throwIt(S)V
				L2:	aload_1;
					invokevirtual 53;		// javacard/framework/APDU.getBuffer()[B
					astore_2;
				L3:	aload_1;
					invokevirtual 85;		// javacard/framework/APDU.setIncomingAndReceive()S
					sstore_3;
				L4:	aload_2;
					sconst_5;
					invokestatic 105;		// javacard/framework/Util.getShort([BS)S
					sstore 4;
				L5:	bspush 7;
					sload 4;
					sadd;
					sstore 5;
				L6:	sload_3;
					sconst_2;
					ssub;
					sload 4;
					ssub;
					sstore 6;
				L7:	getfield_a_this 22;		// reference thegym/thegym.rsaSignature
					getfield_a_this 19;		// reference thegym/thegym.rsaPublicKey
					sconst_2;
					invokevirtual 103;		// javacard/security/Signature.init(Ljavacard/security/Key;B)V
					getfield_a_this 22;		// reference thegym/thegym.rsaSignature
					aload_2;
					bspush 7;
					sload 4;
					aload_2;
					sload 5;
					sload 6;
					invokevirtual 106;		// javacard/security/Signature.verify([BSS[BSS)Z
					sstore 7;
				L8:	aload_2;
					sconst_0;
					sload 7;
					ifeq L10;
				L9:	sconst_1;
					goto L11;
				L10:	sconst_0;
				L11:	bastore;
					aload_1;
					sconst_0;
					sconst_1;
					invokevirtual 84;		// javacard/framework/APDU.setOutgoingAndSend(SS)V
					return;
		}

		.method private decapsulateSessionKey([BS)Z {
			.stack 6;
			.locals 1;

				L0:	getfield_b_this 24;		// boolean thegym/thegym.rsaKeysGenerated
					ifne L2;
				L1:	sconst_0;
					sreturn;
				L2:	getfield_a_this 21;		// reference thegym/thegym.rsaCipher
					getfield_a_this 20;		// reference thegym/thegym.rsaPrivateKey
					sconst_1;
					invokevirtual 90;		// javacardx/crypto/Cipher.init(Ljavacard/security/Key;B)V
					getfield_a_this 21;		// reference thegym/thegym.rsaCipher
					aload_1;
					sload_2;
					sspush 128;
					getfield_a_this 7;		// reference thegym/thegym.tempBuffer2
					sconst_0;
					invokevirtual 91;		// javacardx/crypto/Cipher.doFinal([BSS[BS)S
					sstore_3;
				L3:	sload_3;
					bspush 32;
					if_scmpeq L6;
				L4:	sconst_0;
				L5:	sreturn;
				L6:	getfield_a_this 7;		// reference thegym/thegym.tempBuffer2
					sconst_0;
					getfield_a_this 10;		// reference thegym/thegym.sessionKeyBuffer
					sconst_0;
					bspush 16;
					invokestatic 50;		// javacard/framework/Util.arrayCopy([BS[BSS)S
					pop;
					getfield_a_this 7;		// reference thegym/thegym.tempBuffer2
					bspush 16;
					getfield_a_this 11;		// reference thegym/thegym.sessionIvBuffer
					sconst_0;
					bspush 16;
					invokestatic 50;		// javacard/framework/Util.arrayCopy([BS[BSS)S
					pop;
					getfield_a_this 17;		// reference thegym/thegym.sessionAesKey
					getfield_a_this 10;		// reference thegym/thegym.sessionKeyBuffer
					sconst_0;
					invokeinterface 3 43 4;		// javacard/security/AESKey
					sconst_1;
				L7:	sreturn;
				L8:	astore_3;
				L9:	sconst_0;
					sreturn;
			.exceptionTable {
				// start_block end_block handler_block catch_type_index
				L2 L5 L8 38;
				L6 L7 L8 38;
			}
		}

		.method private processUpdateInfoEncaps(Ljavacard/framework/APDU;)V {
			.stack 6;
			.locals 13;

			.descriptor	Ljavacard/framework/APDU;	0.10;

				L0:	getfield_a_this 0;		// reference thegym/thegym.pin
					invokevirtual 83;		// javacard/framework/OwnerPIN.isValidated()Z
					ifne L2;
				L1:	sspush 27010;
					invokestatic 55;		// javacard/framework/ISOException.throwIt(S)V
				L2:	getfield_b_this 25;		// boolean thegym/thegym.masterKeyDerived
					ifne L4;
				L3:	sspush 27013;
					invokestatic 55;		// javacard/framework/ISOException.throwIt(S)V
				L4:	aload_1;
					invokevirtual 53;		// javacard/framework/APDU.getBuffer()[B
					astore_2;
				L5:	aload_1;
					invokevirtual 85;		// javacard/framework/APDU.setIncomingAndReceive()S
					sstore_3;
				L6:	getfield_a_this 15;		// reference thegym/thegym.aesCipher
					getfield_a_this 17;		// reference thegym/thegym.sessionAesKey
					sconst_1;
					getfield_a_this 11;		// reference thegym/thegym.sessionIvBuffer
					sconst_0;
					bspush 16;
					invokevirtual 95;		// javacardx/crypto/Cipher.init(Ljavacard/security/Key;B[BSS)V
					getfield_a_this 15;		// reference thegym/thegym.aesCipher
					aload_2;
					sconst_5;
					sload_3;
					getfield_a_this 6;		// reference thegym/thegym.tempBuffer
					sconst_0;
					invokevirtual 91;		// javacardx/crypto/Cipher.doFinal([BSS[BS)S
					sstore 4;
				L7:	getfield_a_this 6;		// reference thegym/thegym.tempBuffer
					sload 4;
					sconst_1;
					ssub;
					baload;
					sstore 5;
				L8:	sload 5;
					ifle L11;
				L9:	sload 5;
					bspush 16;
					if_scmpgt L11;
				L10:	sload 4;
					sload 5;
					ssub;
					sstore 4;
				L11:	sconst_0;
					sstore 6;
				L12:	sconst_0;
					sstore 7;
				L13:	getfield_a_this 6;		// reference thegym/thegym.tempBuffer
					sload 6;
					sinc 6 1;
					baload;
					sstore 8;
				L14:	getfield_a_this 2;		// reference thegym/thegym.userData
					sconst_0;
					sspush 1024;
					sconst_0;
					invokestatic 51;		// javacard/framework/Util.arrayFillNonAtomic([BSSB)S
					pop;
					getfield_a_this 2;		// reference thegym/thegym.userData
					sload 7;
					sinc 7 1;
					sload 8;
					bastore;
					sconst_0;
					sstore 9;
				L15:	sload 9;
					sload 8;
					if_scmpge_w L25;
				L16:	getfield_a_this 6;		// reference thegym/thegym.tempBuffer
					sload 6;
					sinc 6 1;
					baload;
					sstore 10;
				L17:	getfield_a_this 6;		// reference thegym/thegym.tempBuffer
					sload 6;
					invokestatic 105;		// javacard/framework/Util.getShort([BS)S
					sstore 11;
				L18:	sinc 6 2;
					getfield_a_this 6;		// reference thegym/thegym.tempBuffer
					sload 6;
					getfield_a_this 7;		// reference thegym/thegym.tempBuffer2
					sconst_0;
					sload 11;
					invokestatic 50;		// javacard/framework/Util.arrayCopy([BS[BSS)S
					pop;
					sload 11;
					s2i;
					bipush 16;
					iadd;
					bipush 16;
					idiv;
					bipush 16;
					imul;
					i2s;
					sstore 12;
				L19:	sload 12;
					sload 11;
					ssub;
					s2b;
					sstore 13;
				L20:	sload 11;
					sstore 14;
				L21:	sload 14;
					sload 12;
					if_scmpge L23;
				L22:	getfield_a_this 7;		// reference thegym/thegym.tempBuffer2
					sload 14;
					sload 13;
					bastore;
					sinc 14 1;
					goto L21;
				L23:	getfield_a_this 2;		// reference thegym/thegym.userData
					sload 7;
					sinc 7 1;
					sload 10;
					bastore;
					getfield_a_this 2;		// reference thegym/thegym.userData
					sload 7;
					sload 12;
					invokestatic 107;		// javacard/framework/Util.setShort([BSS)S
					pop;
					sinc 7 2;
					getfield_a_this 15;		// reference thegym/thegym.aesCipher
					getfield_a_this 16;		// reference thegym/thegym.masterKey
					sconst_2;
					getfield_a_this 9;		// reference thegym/thegym.masterIvBuffer
					sconst_0;
					bspush 16;
					invokevirtual 95;		// javacardx/crypto/Cipher.init(Ljavacard/security/Key;B[BSS)V
					getfield_a_this 15;		// reference thegym/thegym.aesCipher
					getfield_a_this 7;		// reference thegym/thegym.tempBuffer2
					sconst_0;
					sload 12;
					getfield_a_this 2;		// reference thegym/thegym.userData
					sload 7;
					invokevirtual 91;		// javacardx/crypto/Cipher.doFinal([BSS[BS)S
					pop;
					sload 7;
					sload 12;
					sadd;
					sstore 7;
					sload 6;
					sload 11;
					sadd;
					sstore 6;
				L24:	sload 9;
					sconst_1;
					sadd;
					s2b;
					sstore 9;
					goto_w L15;
				L25:	aload_0;
					sload 7;
					putfield_s 26;		// short thegym/thegym.userDataLen
					getfield_a_this 6;		// reference thegym/thegym.tempBuffer
					sconst_0;
					sload 4;
					sconst_0;
					invokestatic 51;		// javacard/framework/Util.arrayFillNonAtomic([BSSB)S
					pop;
					getfield_a_this 7;		// reference thegym/thegym.tempBuffer2
					sconst_0;
					sspush 256;
					sconst_0;
					invokestatic 51;		// javacard/framework/Util.arrayFillNonAtomic([BSSB)S
					pop;
					aload_2;
					sconst_0;
					sconst_1;
					bastore;
					aload_1;
					sconst_0;
					sconst_1;
					invokevirtual 84;		// javacard/framework/APDU.setOutgoingAndSend(SS)V
					return;
		}

		.method private processGetInfoEncaps(Ljavacard/framework/APDU;)V {
			.stack 6;
			.locals 8;

			.descriptor	Ljavacard/framework/APDU;	0.10;

				L0:	getfield_a_this 0;		// reference thegym/thegym.pin
					invokevirtual 83;		// javacard/framework/OwnerPIN.isValidated()Z
					ifeq L2;
				L1:	getfield_b_this 25;		// boolean thegym/thegym.masterKeyDerived
					ifne L3;
				L2:	sspush 27013;
					invokestatic 55;		// javacard/framework/ISOException.throwIt(S)V
				L3:	getfield_s_this 26;		// short thegym/thegym.userDataLen
					ifne L5;
				L4:	sspush 27013;
					invokestatic 55;		// javacard/framework/ISOException.throwIt(S)V
				L5:	sconst_0;
					sstore_2;
				L6:	sconst_0;
					sstore_3;
				L7:	getfield_a_this 2;		// reference thegym/thegym.userData
					sload_2;
					sinc 2 1;
					baload;
					sstore 4;
				L8:	getfield_a_this 6;		// reference thegym/thegym.tempBuffer
					sload_3;
					sinc 3 1;
					sload 4;
					bastore;
					sconst_0;
					sstore 5;
				L9:	sload 5;
					sload 4;
					if_scmpge_w L19;
				L10:	getfield_a_this 2;		// reference thegym/thegym.userData
					sload_2;
					sinc 2 1;
					baload;
					sstore 6;
				L11:	getfield_a_this 2;		// reference thegym/thegym.userData
					sload_2;
					invokestatic 105;		// javacard/framework/Util.getShort([BS)S
					sstore 7;
				L12:	sinc 2 2;
					getfield_a_this 15;		// reference thegym/thegym.aesCipher
					getfield_a_this 16;		// reference thegym/thegym.masterKey
					sconst_1;
					getfield_a_this 9;		// reference thegym/thegym.masterIvBuffer
					sconst_0;
					bspush 16;
					invokevirtual 95;		// javacardx/crypto/Cipher.init(Ljavacard/security/Key;B[BSS)V
					getfield_a_this 15;		// reference thegym/thegym.aesCipher
					getfield_a_this 2;		// reference thegym/thegym.userData
					sload_2;
					sload 7;
					getfield_a_this 7;		// reference thegym/thegym.tempBuffer2
					sconst_0;
					invokevirtual 91;		// javacardx/crypto/Cipher.doFinal([BSS[BS)S
					sstore 8;
				L13:	getfield_a_this 7;		// reference thegym/thegym.tempBuffer2
					sload 8;
					sconst_1;
					ssub;
					baload;
					sstore 9;
				L14:	sload 9;
					ifle L17;
				L15:	sload 9;
					bspush 16;
					if_scmpgt L17;
				L16:	sload 8;
					sload 9;
					ssub;
					sstore 8;
				L17:	getfield_a_this 6;		// reference thegym/thegym.tempBuffer
					sload_3;
					sinc 3 1;
					sload 6;
					bastore;
					getfield_a_this 6;		// reference thegym/thegym.tempBuffer
					sload_3;
					sload 8;
					invokestatic 107;		// javacard/framework/Util.setShort([BSS)S
					pop;
					sinc 3 2;
					getfield_a_this 7;		// reference thegym/thegym.tempBuffer2
					sconst_0;
					getfield_a_this 6;		// reference thegym/thegym.tempBuffer
					sload_3;
					sload 8;
					invokestatic 50;		// javacard/framework/Util.arrayCopy([BS[BSS)S
					pop;
					sload_3;
					sload 8;
					sadd;
					sstore_3;
					sload_2;
					sload 7;
					sadd;
					sstore_2;
				L18:	sload 5;
					sconst_1;
					sadd;
					s2b;
					sstore 5;
					goto_w L9;
				L19:	aload_1;
					invokevirtual 53;		// javacard/framework/APDU.getBuffer()[B
					astore 5;
				L20:	sload_3;
					sstore 6;
				L21:	sload 6;
					s2i;
					bipush 16;
					iadd;
					bipush 16;
					idiv;
					bipush 16;
					imul;
					i2s;
					sstore 7;
				L22:	sload 7;
					sload 6;
					ssub;
					s2b;
					sstore 8;
				L23:	sload 6;
					sstore 9;
				L24:	sload 9;
					sload 7;
					if_scmpge L26;
				L25:	getfield_a_this 6;		// reference thegym/thegym.tempBuffer
					sload 9;
					sload 8;
					bastore;
					sinc 9 1;
					goto L24;
				L26:	getfield_a_this 15;		// reference thegym/thegym.aesCipher
					getfield_a_this 17;		// reference thegym/thegym.sessionAesKey
					sconst_2;
					getfield_a_this 11;		// reference thegym/thegym.sessionIvBuffer
					sconst_0;
					bspush 16;
					invokevirtual 95;		// javacardx/crypto/Cipher.init(Ljavacard/security/Key;B[BSS)V
					getfield_a_this 15;		// reference thegym/thegym.aesCipher
					getfield_a_this 6;		// reference thegym/thegym.tempBuffer
					sconst_0;
					sload 7;
					aload 5;
					sconst_0;
					invokevirtual 91;		// javacardx/crypto/Cipher.doFinal([BSS[BS)S
					sstore 9;
				L27:	aload_1;
					sconst_0;
					sload 9;
					invokevirtual 84;		// javacard/framework/APDU.setOutgoingAndSend(SS)V
					return;
		}

		.method private processUploadAvatarEncaps(Ljavacard/framework/APDU;)V {
			.stack 6;
			.locals 11;

			.descriptor	Ljavacard/framework/APDU;	0.10;

				L0:	getfield_a_this 0;		// reference thegym/thegym.pin
					invokevirtual 83;		// javacard/framework/OwnerPIN.isValidated()Z
					ifne L2;
				L1:	sspush 27010;
					invokestatic 55;		// javacard/framework/ISOException.throwIt(S)V
				L2:	getfield_b_this 24;		// boolean thegym/thegym.rsaKeysGenerated
					ifeq L4;
				L3:	getfield_b_this 25;		// boolean thegym/thegym.masterKeyDerived
					ifne L5;
				L4:	sspush 27013;
					invokestatic 55;		// javacard/framework/ISOException.throwIt(S)V
				L5:	aload_1;
					invokevirtual 53;		// javacard/framework/APDU.getBuffer()[B
					astore_2;
				L6:	aload_2;
					sconst_2;
					baload;
					sstore_3;
				L7:	aload_2;
					sconst_3;
					baload;
					sstore 4;
				L8:	sload_3;
					bspush 127;
					sand;
					bspush 8;
					sshl;
					sload 4;
					sspush 255;
					sand;
					sor;
					sstore 5;
				L9:	sload_3;
					sspush 128;
					sand;
					ifeq L11;
				L10:	sconst_1;
					goto L12;
				L11:	sconst_0;
				L12:	sstore 6;
				L13:	aload_1;
					invokevirtual 85;		// javacard/framework/APDU.setIncomingAndReceive()S
					sstore 7;
				L14:	sload 5;
					ifne_w L29;
				L15:	sload 7;
					sspush 128;
					if_scmpge L17;
				L16:	sspush 26368;
					invokestatic 55;		// javacard/framework/ISOException.throwIt(S)V
				L17:	aload_0;
					aload_2;
					sconst_5;
					invokespecial 86;		// thegym/thegym.decapsulateSessionKey([BS)Z
					ifne L19;
				L18:	sspush 27012;
					invokestatic 55;		// javacard/framework/ISOException.throwIt(S)V
				L19:	aload_0;
					sconst_0;
					putfield_s 27;		// short thegym/thegym.avatarCurrentSize
					sspush 133;
					sstore 8;
				L20:	sload 7;
					sspush 128;
					ssub;
					sstore 9;
				L21:	sload 9;
					ifle L28;
				L22:	sload 9;
					bspush 16;
					srem;
					ifeq L24;
				L23:	sspush 26368;
					invokestatic 55;		// javacard/framework/ISOException.throwIt(S)V
				L24:	getfield_a_this 15;		// reference thegym/thegym.aesCipher
					getfield_a_this 17;		// reference thegym/thegym.sessionAesKey
					sconst_1;
					getfield_a_this 11;		// reference thegym/thegym.sessionIvBuffer
					sconst_0;
					bspush 16;
					invokevirtual 95;		// javacardx/crypto/Cipher.init(Ljavacard/security/Key;B[BSS)V
					getfield_a_this 15;		// reference thegym/thegym.aesCipher
					aload_2;
					sload 8;
					sload 9;
					getfield_a_this 6;		// reference thegym/thegym.tempBuffer
					sconst_0;
					invokevirtual 91;		// javacardx/crypto/Cipher.doFinal([BSS[BS)S
					sstore 10;
				L25:	sload 10;
					sspush 10240;
					if_scmple L27;
				L26:	sspush 27268;
					invokestatic 55;		// javacard/framework/ISOException.throwIt(S)V
				L27:	getfield_a_this 6;		// reference thegym/thegym.tempBuffer
					sconst_0;
					getfield_a_this 3;		// reference thegym/thegym.avatarData
					sconst_0;
					sload 10;
					invokestatic 50;		// javacard/framework/Util.arrayCopy([BS[BSS)S
					pop;
					aload_0;
					sload 10;
					putfield_s 27;		// short thegym/thegym.avatarCurrentSize
				L28:	goto L36;
				L29:	sload 7;
					ifle L36;
				L30:	sload 7;
					bspush 16;
					srem;
					ifeq L32;
				L31:	sspush 26368;
					invokestatic 55;		// javacard/framework/ISOException.throwIt(S)V
				L32:	getfield_a_this 15;		// reference thegym/thegym.aesCipher
					getfield_a_this 17;		// reference thegym/thegym.sessionAesKey
					sconst_1;
					getfield_a_this 11;		// reference thegym/thegym.sessionIvBuffer
					sconst_0;
					bspush 16;
					invokevirtual 95;		// javacardx/crypto/Cipher.init(Ljavacard/security/Key;B[BSS)V
					getfield_a_this 15;		// reference thegym/thegym.aesCipher
					aload_2;
					sconst_5;
					sload 7;
					getfield_a_this 6;		// reference thegym/thegym.tempBuffer
					sconst_0;
					invokevirtual 91;		// javacardx/crypto/Cipher.doFinal([BSS[BS)S
					sstore 8;
				L33:	getfield_s_this 27;		// short thegym/thegym.avatarCurrentSize
					sload 8;
					sadd;
					sspush 10240;
					if_scmple L35;
				L34:	sspush 27268;
					invokestatic 55;		// javacard/framework/ISOException.throwIt(S)V
				L35:	getfield_a_this 6;		// reference thegym/thegym.tempBuffer
					sconst_0;
					getfield_a_this 3;		// reference thegym/thegym.avatarData
					getfield_s_this 27;		// short thegym/thegym.avatarCurrentSize
					sload 8;
					invokestatic 50;		// javacard/framework/Util.arrayCopy([BS[BSS)S
					pop;
					aload_0;
					dup;
					getfield_s 27;		// short thegym/thegym.avatarCurrentSize
					sload 8;
					sadd;
					putfield_s 27;		// short thegym/thegym.avatarCurrentSize
				L36:	sload 6;
					ifeq_w L57;
				L37:	getfield_s_this 27;		// short thegym/thegym.avatarCurrentSize
					ifle_w L57;
				L38:	getfield_a_this 3;		// reference thegym/thegym.avatarData
					getfield_s_this 27;		// short thegym/thegym.avatarCurrentSize
					sconst_1;
					ssub;
					baload;
					sstore 8;
				L39:	sload 8;
					ifle L49;
				L40:	sload 8;
					bspush 16;
					if_scmpgt L49;
				L41:	sconst_1;
					sstore 9;
				L42:	getfield_s_this 27;		// short thegym/thegym.avatarCurrentSize
					sload 8;
					ssub;
					sstore 10;
				L43:	sload 10;
					getfield_s_this 27;		// short thegym/thegym.avatarCurrentSize
					if_scmpge L47;
				L44:	getfield_a_this 3;		// reference thegym/thegym.avatarData
					sload 10;
					baload;
					sload 8;
					if_scmpeq L46;
				L45:	sconst_0;
					sstore 9;
					goto L47;
				L46:	sinc 10 1;
					goto L43;
				L47:	sload 9;
					ifeq L49;
				L48:	aload_0;
					dup;
					getfield_s 27;		// short thegym/thegym.avatarCurrentSize
					sload 8;
					ssub;
					putfield_s 27;		// short thegym/thegym.avatarCurrentSize
				L49:	getfield_s_this 27;		// short thegym/thegym.avatarCurrentSize
					sstore 9;
				L50:	sload 9;
					s2i;
					bipush 16;
					iadd;
					bipush 16;
					idiv;
					bipush 16;
					imul;
					i2s;
					sstore 10;
				L51:	sload 10;
					sload 9;
					ssub;
					s2b;
					sstore 11;
				L52:	getfield_a_this 3;		// reference thegym/thegym.avatarData
					sconst_0;
					getfield_a_this 6;		// reference thegym/thegym.tempBuffer
					sconst_0;
					sload 9;
					invokestatic 50;		// javacard/framework/Util.arrayCopy([BS[BSS)S
					pop;
					sload 9;
					sstore 12;
				L53:	sload 12;
					sload 10;
					if_scmpge L55;
				L54:	getfield_a_this 6;		// reference thegym/thegym.tempBuffer
					sload 12;
					sload 11;
					bastore;
					sinc 12 1;
					goto L53;
				L55:	getfield_a_this 15;		// reference thegym/thegym.aesCipher
					getfield_a_this 16;		// reference thegym/thegym.masterKey
					sconst_2;
					getfield_a_this 9;		// reference thegym/thegym.masterIvBuffer
					sconst_0;
					bspush 16;
					invokevirtual 95;		// javacardx/crypto/Cipher.init(Ljavacard/security/Key;B[BSS)V
					getfield_a_this 15;		// reference thegym/thegym.aesCipher
					getfield_a_this 6;		// reference thegym/thegym.tempBuffer
					sconst_0;
					sload 10;
					getfield_a_this 3;		// reference thegym/thegym.avatarData
					sconst_0;
					invokevirtual 91;		// javacardx/crypto/Cipher.doFinal([BSS[BS)S
					sstore 12;
				L56:	aload_0;
					sload 12;
					putfield_s 27;		// short thegym/thegym.avatarCurrentSize
					aload_2;
					sconst_0;
					sload 9;
					bspush 8;
					sshr;
					sspush 255;
					sand;
					s2b;
					bastore;
					aload_2;
					sconst_1;
					sload 9;
					sspush 255;
					sand;
					s2b;
					bastore;
					aload_1;
					sconst_0;
					sconst_2;
					invokevirtual 84;		// javacard/framework/APDU.setOutgoingAndSend(SS)V
					return;
				L57:	return;
		}

		.method private processGetAvatarEncaps(Ljavacard/framework/APDU;)V {
			.stack 6;
			.locals 11;

			.descriptor	Ljavacard/framework/APDU;	0.10;

				L0:	getfield_a_this 0;		// reference thegym/thegym.pin
					invokevirtual 83;		// javacard/framework/OwnerPIN.isValidated()Z
					ifne L2;
				L1:	sspush 27010;
					invokestatic 55;		// javacard/framework/ISOException.throwIt(S)V
				L2:	getfield_b_this 24;		// boolean thegym/thegym.rsaKeysGenerated
					ifeq L4;
				L3:	getfield_b_this 25;		// boolean thegym/thegym.masterKeyDerived
					ifne L5;
				L4:	sspush 27013;
					invokestatic 55;		// javacard/framework/ISOException.throwIt(S)V
				L5:	aload_1;
					invokevirtual 53;		// javacard/framework/APDU.getBuffer()[B
					astore_2;
				L6:	aload_2;
					sconst_2;
					baload;
					sstore_3;
				L7:	aload_2;
					sconst_3;
					baload;
					sstore 4;
				L8:	aload_1;
					invokevirtual 85;		// javacard/framework/APDU.setIncomingAndReceive()S
					sstore 5;
				L9:	getfield_s_this 27;		// short thegym/thegym.avatarCurrentSize
					ifne L11;
				L10:	aload_2;
					sconst_0;
					sconst_0;
					bastore;
					aload_2;
					sconst_1;
					sconst_0;
					bastore;
					aload_1;
					sconst_0;
					sconst_2;
					invokevirtual 84;		// javacard/framework/APDU.setOutgoingAndSend(SS)V
					return;
				L11:	sload_3;
					ifne_w L23;
				L12:	sload 4;
					ifne_w L23;
				L13:	sload 5;
					sspush 128;
					if_scmpeq L15;
				L14:	sspush 26368;
					invokestatic 55;		// javacard/framework/ISOException.throwIt(S)V
				L15:	aload_0;
					aload_2;
					sconst_5;
					invokespecial 86;		// thegym/thegym.decapsulateSessionKey([BS)Z
					ifne L17;
				L16:	sspush 27012;
					invokestatic 55;		// javacard/framework/ISOException.throwIt(S)V
				L17:	getfield_a_this 15;		// reference thegym/thegym.aesCipher
					getfield_a_this 16;		// reference thegym/thegym.masterKey
					sconst_1;
					getfield_a_this 9;		// reference thegym/thegym.masterIvBuffer
					sconst_0;
					bspush 16;
					invokevirtual 95;		// javacardx/crypto/Cipher.init(Ljavacard/security/Key;B[BSS)V
					getfield_a_this 15;		// reference thegym/thegym.aesCipher
					getfield_a_this 3;		// reference thegym/thegym.avatarData
					sconst_0;
					getfield_s_this 27;		// short thegym/thegym.avatarCurrentSize
					getfield_a_this 6;		// reference thegym/thegym.tempBuffer
					sconst_0;
					invokevirtual 91;		// javacardx/crypto/Cipher.doFinal([BSS[BS)S
					sstore 6;
				L18:	getfield_a_this 6;		// reference thegym/thegym.tempBuffer
					sload 6;
					sconst_1;
					ssub;
					baload;
					sstore 7;
				L19:	sload 7;
					ifle L22;
				L20:	sload 7;
					bspush 16;
					if_scmpgt L22;
				L21:	sload 6;
					sload 7;
					ssub;
					sstore 6;
				L22:	getfield_a_this 12;		// reference thegym/thegym.hashBuffer
					sconst_0;
					sload 6;
					bspush 8;
					sshr;
					sspush 255;
					sand;
					s2b;
					bastore;
					getfield_a_this 12;		// reference thegym/thegym.hashBuffer
					sconst_1;
					sload 6;
					sspush 255;
					sand;
					s2b;
					bastore;
					getfield_a_this 12;		// reference thegym/thegym.hashBuffer
					sconst_2;
					sconst_1;
					bastore;
					getfield_a_this 6;		// reference thegym/thegym.tempBuffer
					sconst_0;
					getfield_a_this 3;		// reference thegym/thegym.avatarData
					sconst_0;
					sload 6;
					invokestatic 50;		// javacard/framework/Util.arrayCopy([BS[BSS)S
					pop;
					aload_2;
					sconst_0;
					getfield_a_this 12;		// reference thegym/thegym.hashBuffer
					sconst_0;
					baload;
					bastore;
					aload_2;
					sconst_1;
					getfield_a_this 12;		// reference thegym/thegym.hashBuffer
					sconst_1;
					baload;
					bastore;
					aload_1;
					sconst_0;
					sconst_2;
					invokevirtual 84;		// javacard/framework/APDU.setOutgoingAndSend(SS)V
					return;
				L23:	getfield_a_this 12;		// reference thegym/thegym.hashBuffer
					sconst_2;
					baload;
					sconst_1;
					if_scmpeq L25;
				L24:	sspush 27013;
					invokestatic 55;		// javacard/framework/ISOException.throwIt(S)V
				L25:	sload_3;
					bspush 8;
					sshl;
					sload 4;
					sspush 255;
					sand;
					sor;
					sstore 6;
				L26:	getfield_a_this 12;		// reference thegym/thegym.hashBuffer
					sconst_0;
					baload;
					sspush 255;
					sand;
					bspush 8;
					sshl;
					getfield_a_this 12;		// reference thegym/thegym.hashBuffer
					sconst_1;
					baload;
					sspush 255;
					sand;
					sor;
					sstore 7;
				L27:	sload 6;
					sload 7;
					if_scmplt L29;
				L28:	aload_0;
					sload 7;
					invokespecial 108;		// thegym/thegym.reEncryptAvatarWithMasterKey(S)V
					aload_1;
					sconst_0;
					sconst_0;
					invokevirtual 84;		// javacard/framework/APDU.setOutgoingAndSend(SS)V
					return;
				L29:	sload 7;
					sload 6;
					ssub;
					sstore 8;
				L30:	sload 8;
					bspush 100;
					if_scmple L32;
				L31:	bspush 100;
					goto L33;
				L32:	sload 8;
				L33:	sstore 9;
				L34:	getfield_a_this 3;		// reference thegym/thegym.avatarData
					sload 6;
					getfield_a_this 6;		// reference thegym/thegym.tempBuffer
					sconst_0;
					sload 9;
					invokestatic 50;		// javacard/framework/Util.arrayCopy([BS[BSS)S
					pop;
					sload 9;
					s2i;
					bipush 16;
					iadd;
					bipush 16;
					idiv;
					bipush 16;
					imul;
					i2s;
					sstore 10;
				L35:	sload 10;
					sload 9;
					ssub;
					s2b;
					sstore 11;
				L36:	sload 9;
					sstore 12;
				L37:	sload 12;
					sload 10;
					if_scmpge L39;
				L38:	getfield_a_this 6;		// reference thegym/thegym.tempBuffer
					sload 12;
					sload 11;
					bastore;
					sinc 12 1;
					goto L37;
				L39:	getfield_a_this 15;		// reference thegym/thegym.aesCipher
					getfield_a_this 17;		// reference thegym/thegym.sessionAesKey
					sconst_2;
					getfield_a_this 11;		// reference thegym/thegym.sessionIvBuffer
					sconst_0;
					bspush 16;
					invokevirtual 95;		// javacardx/crypto/Cipher.init(Ljavacard/security/Key;B[BSS)V
					getfield_a_this 15;		// reference thegym/thegym.aesCipher
					getfield_a_this 6;		// reference thegym/thegym.tempBuffer
					sconst_0;
					sload 10;
					aload_2;
					sconst_0;
					invokevirtual 91;		// javacardx/crypto/Cipher.doFinal([BSS[BS)S
					sstore 12;
				L40:	aload_1;
					sconst_0;
					sload 12;
					invokevirtual 84;		// javacard/framework/APDU.setOutgoingAndSend(SS)V
				L41:	return;
		}

		.method private reEncryptAvatarWithMasterKey(S)V {
			.stack 6;
			.locals 3;

				L0:	sload_1;
					ifgt L2;
				L1:	return;
				L2:	getfield_a_this 3;		// reference thegym/thegym.avatarData
					sconst_0;
					getfield_a_this 6;		// reference thegym/thegym.tempBuffer
					sconst_0;
					sload_1;
					invokestatic 50;		// javacard/framework/Util.arrayCopy([BS[BSS)S
					pop;
					sload_1;
					s2i;
					bipush 16;
					iadd;
					bipush 16;
					idiv;
					bipush 16;
					imul;
					i2s;
					sstore_2;
				L3:	sload_2;
					sload_1;
					ssub;
					s2b;
					sstore_3;
				L4:	sload_1;
					sstore 4;
				L5:	sload 4;
					sload_2;
					if_scmpge L7;
				L6:	getfield_a_this 6;		// reference thegym/thegym.tempBuffer
					sload 4;
					sload_3;
					bastore;
					sinc 4 1;
					goto L5;
				L7:	getfield_a_this 15;		// reference thegym/thegym.aesCipher
					getfield_a_this 16;		// reference thegym/thegym.masterKey
					sconst_2;
					getfield_a_this 9;		// reference thegym/thegym.masterIvBuffer
					sconst_0;
					bspush 16;
					invokevirtual 95;		// javacardx/crypto/Cipher.init(Ljavacard/security/Key;B[BSS)V
					getfield_a_this 15;		// reference thegym/thegym.aesCipher
					getfield_a_this 6;		// reference thegym/thegym.tempBuffer
					sconst_0;
					sload_2;
					getfield_a_this 3;		// reference thegym/thegym.avatarData
					sconst_0;
					invokevirtual 91;		// javacardx/crypto/Cipher.doFinal([BSS[BS)S
					sstore 4;
				L8:	aload_0;
					sload 4;
					putfield_s 27;		// short thegym/thegym.avatarCurrentSize
					getfield_a_this 12;		// reference thegym/thegym.hashBuffer
					sconst_2;
					sconst_0;
					bastore;
					return;
		}

		.method private processHashData(Ljavacard/framework/APDU;)V {
			.stack 6;
			.locals 3;

			.descriptor	Ljavacard/framework/APDU;	0.10;

				L0:	getfield_b_this 23;		// boolean thegym/thegym.cryptoInitialized
					ifne L3;
				L1:	aload_0;
					invokespecial 87;		// thegym/thegym.initCrypto()Z
					ifne L3;
				L2:	sspush 27013;
					invokestatic 55;		// javacard/framework/ISOException.throwIt(S)V
				L3:	aload_1;
					invokevirtual 53;		// javacard/framework/APDU.getBuffer()[B
					astore_2;
				L4:	aload_1;
					invokevirtual 85;		// javacard/framework/APDU.setIncomingAndReceive()S
					sstore_3;
				L5:	getfield_a_this 13;		// reference thegym/thegym.sha1
					invokevirtual 47;		// javacard/security/MessageDigest.reset()V
					getfield_a_this 13;		// reference thegym/thegym.sha1
					aload_2;
					sconst_5;
					sload_3;
					getfield_a_this 6;		// reference thegym/thegym.tempBuffer
					sconst_0;
					invokevirtual 49;		// javacard/security/MessageDigest.doFinal([BSS[BS)S
					sstore 4;
				L6:	getfield_a_this 6;		// reference thegym/thegym.tempBuffer
					sconst_0;
					aload_2;
					sconst_0;
					sload 4;
					invokestatic 50;		// javacard/framework/Util.arrayCopy([BS[BSS)S
					pop;
					aload_1;
					sconst_0;
					sload 4;
					invokevirtual 84;		// javacard/framework/APDU.setOutgoingAndSend(SS)V
					return;
		}

		.method private processTransaction(Ljavacard/framework/APDU;Z)V {
			.stack 3;
			.locals 3;

			.descriptor	Ljavacard/framework/APDU;	0.10;

				L0:	getfield_a_this 0;		// reference thegym/thegym.pin
					invokevirtual 83;		// javacard/framework/OwnerPIN.isValidated()Z
					ifne L2;
				L1:	sspush 27010;
					invokestatic 55;		// javacard/framework/ISOException.throwIt(S)V
				L2:	aload_1;
					invokevirtual 53;		// javacard/framework/APDU.getBuffer()[B
					astore_3;
				L3:	aload_3;
					sconst_2;
					baload;
					sspush 255;
					sand;
					sstore 4;
				L4:	sload 4;
					ifne L6;
				L5:	sspush 27264;
					invokestatic 55;		// javacard/framework/ISOException.throwIt(S)V
				L6:	invokestatic 109;		// javacard/framework/JCSystem.beginTransaction()V
					sload_2;
					ifeq L9;
				L7:	aload_0;
					getfield_s_this 29;		// short thegym/thegym.balance
					sload 4;
					sadd;
					putfield_s 29;		// short thegym/thegym.balance
					sconst_1;
					sstore 5;
				L8:	goto L12;
				L9:	getfield_s_this 29;		// short thegym/thegym.balance
					sload 4;
					if_scmpge L11;
				L10:	invokestatic 110;		// javacard/framework/JCSystem.abortTransaction()V
					sspush 26881;
					invokestatic 55;		// javacard/framework/ISOException.throwIt(S)V
				L11:	aload_0;
					getfield_s_this 29;		// short thegym/thegym.balance
					sload 4;
					ssub;
					putfield_s 29;		// short thegym/thegym.balance
					sconst_2;
					sstore 5;
				L12:	aload_0;
					sload 5;
					sload 4;
					invokespecial 111;		// thegym/thegym.logTransaction(BS)V
					invokestatic 112;		// javacard/framework/JCSystem.commitTransaction()V
					aload_3;
					sconst_0;
					getfield_s_this 29;		// short thegym/thegym.balance
					invokestatic 107;		// javacard/framework/Util.setShort([BSS)S
					pop;
					aload_1;
					sconst_0;
					sconst_2;
					invokevirtual 84;		// javacard/framework/APDU.setOutgoingAndSend(SS)V
					return;
		}

		.method private logTransaction(BS)V {
			.stack 3;
			.locals 1;

				L0:	getfield_b_this 30;		// byte thegym/thegym.historyIndex
					sconst_4;
					smul;
					sstore_3;
				L1:	getfield_a_this 5;		// reference thegym/thegym.transactionHistory
					sload_3;
					sload_1;
					bastore;
					getfield_a_this 5;		// reference thegym/thegym.transactionHistory
					sload_3;
					sconst_1;
					sadd;
					sload_2;
					invokestatic 107;		// javacard/framework/Util.setShort([BSS)S
					pop;
					getfield_a_this 5;		// reference thegym/thegym.transactionHistory
					sload_3;
					sconst_3;
					sadd;
					sconst_m1;
					bastore;
					aload_0;
					dup;
					getfield_b 30;		// byte thegym/thegym.historyIndex
					sconst_1;
					sadd;
					s2b;
					putfield_b 30;		// byte thegym/thegym.historyIndex
					getfield_b_this 30;		// byte thegym/thegym.historyIndex
					sconst_5;
					if_scmplt L3;
				L2:	aload_0;
					sconst_0;
					putfield_b 30;		// byte thegym/thegym.historyIndex
				L3:	return;
		}

		.method private processCheckBalance(Ljavacard/framework/APDU;)V {
			.stack 3;
			.locals 1;

			.descriptor	Ljavacard/framework/APDU;	0.10;

				L0:	aload_1;
					invokevirtual 53;		// javacard/framework/APDU.getBuffer()[B
					astore_2;
				L1:	aload_2;
					sconst_0;
					getfield_s_this 29;		// short thegym/thegym.balance
					invokestatic 107;		// javacard/framework/Util.setShort([BSS)S
					pop;
					aload_1;
					sconst_0;
					sconst_2;
					invokevirtual 84;		// javacard/framework/APDU.setOutgoingAndSend(SS)V
					return;
		}

		.method private processGetHistory(Ljavacard/framework/APDU;)V {
			.stack 5;
			.locals 1;

			.descriptor	Ljavacard/framework/APDU;	0.10;

				L0:	aload_1;
					invokevirtual 53;		// javacard/framework/APDU.getBuffer()[B
					astore_2;
				L1:	getfield_a_this 5;		// reference thegym/thegym.transactionHistory
					sconst_0;
					aload_2;
					sconst_0;
					bspush 20;
					invokestatic 50;		// javacard/framework/Util.arrayCopy([BS[BSS)S
					pop;
					aload_1;
					sconst_0;
					bspush 20;
					invokevirtual 84;		// javacard/framework/APDU.setOutgoingAndSend(SS)V
					return;
		}

		.method private processUpdateInfoLegacy(Ljavacard/framework/APDU;)V {
			.stack 6;
			.locals 8;

			.descriptor	Ljavacard/framework/APDU;	0.10;

				L0:	getfield_a_this 0;		// reference thegym/thegym.pin
					invokevirtual 83;		// javacard/framework/OwnerPIN.isValidated()Z
					ifne L2;
				L1:	sspush 27010;
					invokestatic 55;		// javacard/framework/ISOException.throwIt(S)V
				L2:	getfield_b_this 25;		// boolean thegym/thegym.masterKeyDerived
					ifne L4;
				L3:	sspush 27013;
					invokestatic 55;		// javacard/framework/ISOException.throwIt(S)V
				L4:	aload_1;
					invokevirtual 53;		// javacard/framework/APDU.getBuffer()[B
					astore_2;
				L5:	aload_1;
					invokevirtual 85;		// javacard/framework/APDU.setIncomingAndReceive()S
					sstore_3;
				L6:	aload_2;
					sconst_5;
					baload;
					sstore 4;
				L7:	sload 4;
					iflt L9;
				L8:	sload 4;
					bspush 12;
					if_scmple L10;
				L9:	sspush 27264;
					invokestatic 55;		// javacard/framework/ISOException.throwIt(S)V
				L10:	sload 4;
					ifle L12;
				L11:	aload_2;
					bspush 6;
					getfield_a_this 4;		// reference thegym/thegym.recoverySDT
					sconst_0;
					sload 4;
					invokestatic 50;		// javacard/framework/Util.arrayCopy([BS[BSS)S
					pop;
				L12:	aload_0;
					sload 4;
					putfield_b 28;		// byte thegym/thegym.recoverySDTLen
					bspush 6;
					sload 4;
					sadd;
					sstore 5;
				L13:	sload_3;
					sconst_1;
					ssub;
					sload 4;
					ssub;
					sstore 6;
				L14:	sload 6;
					sspush 1024;
					if_scmple L16;
				L15:	sspush 1024;
					sstore 6;
				L16:	sload 6;
					ifle L25;
				L17:	sload 6;
					s2i;
					bipush 16;
					iadd;
					bipush 16;
					idiv;
					bipush 16;
					imul;
					i2s;
					sstore 7;
				L18:	sload 7;
					sload 6;
					ssub;
					s2b;
					sstore 8;
				L19:	sload 6;
					sstore 9;
				L20:	sload 9;
					sload 7;
					if_scmpge L22;
				L21:	aload_2;
					sload 5;
					sload 9;
					sadd;
					sload 8;
					bastore;
					sinc 9 1;
					goto L20;
				L22:	getfield_a_this 15;		// reference thegym/thegym.aesCipher
					getfield_a_this 16;		// reference thegym/thegym.masterKey
					sconst_2;
					getfield_a_this 9;		// reference thegym/thegym.masterIvBuffer
					sconst_0;
					bspush 16;
					invokevirtual 95;		// javacardx/crypto/Cipher.init(Ljavacard/security/Key;B[BSS)V
					getfield_a_this 15;		// reference thegym/thegym.aesCipher
					aload_2;
					sload 5;
					sload 7;
					getfield_a_this 2;		// reference thegym/thegym.userData
					sconst_0;
					invokevirtual 91;		// javacardx/crypto/Cipher.doFinal([BSS[BS)S
					sstore 9;
				L23:	aload_0;
					sload 9;
					putfield_s 26;		// short thegym/thegym.userDataLen
				L24:	goto L26;
				L25:	aload_0;
					sconst_0;
					putfield_s 26;		// short thegym/thegym.userDataLen
				L26:	return;
		}

		.method private processGetInfoLegacy(Ljavacard/framework/APDU;)V {
			.stack 6;
			.locals 3;

			.descriptor	Ljavacard/framework/APDU;	0.10;

				L0:	getfield_a_this 0;		// reference thegym/thegym.pin
					invokevirtual 83;		// javacard/framework/OwnerPIN.isValidated()Z
					ifne L2;
				L1:	sspush 27010;
					invokestatic 55;		// javacard/framework/ISOException.throwIt(S)V
				L2:	getfield_b_this 25;		// boolean thegym/thegym.masterKeyDerived
					ifne L4;
				L3:	sspush 27013;
					invokestatic 55;		// javacard/framework/ISOException.throwIt(S)V
				L4:	getfield_s_this 26;		// short thegym/thegym.userDataLen
					ifne L6;
				L5:	sspush 27013;
					invokestatic 55;		// javacard/framework/ISOException.throwIt(S)V
				L6:	aload_1;
					invokevirtual 53;		// javacard/framework/APDU.getBuffer()[B
					astore_2;
				L7:	getfield_a_this 15;		// reference thegym/thegym.aesCipher
					getfield_a_this 16;		// reference thegym/thegym.masterKey
					sconst_1;
					getfield_a_this 9;		// reference thegym/thegym.masterIvBuffer
					sconst_0;
					bspush 16;
					invokevirtual 95;		// javacardx/crypto/Cipher.init(Ljavacard/security/Key;B[BSS)V
					getfield_a_this 15;		// reference thegym/thegym.aesCipher
					getfield_a_this 2;		// reference thegym/thegym.userData
					sconst_0;
					getfield_s_this 26;		// short thegym/thegym.userDataLen
					getfield_a_this 6;		// reference thegym/thegym.tempBuffer
					sconst_0;
					invokevirtual 91;		// javacardx/crypto/Cipher.doFinal([BSS[BS)S
					sstore_3;
				L8:	getfield_a_this 6;		// reference thegym/thegym.tempBuffer
					sload_3;
					sconst_1;
					ssub;
					baload;
					sstore 4;
				L9:	sload 4;
					ifle L12;
				L10:	sload 4;
					bspush 16;
					if_scmpgt L12;
				L11:	sload_3;
					sload 4;
					ssub;
					sstore_3;
				L12:	getfield_a_this 6;		// reference thegym/thegym.tempBuffer
					sconst_0;
					aload_2;
					sconst_0;
					sload_3;
					invokestatic 50;		// javacard/framework/Util.arrayCopy([BS[BSS)S
					pop;
					aload_1;
					sconst_0;
					sload_3;
					invokevirtual 84;		// javacard/framework/APDU.setOutgoingAndSend(SS)V
					return;
		}

		.method private processUploadAvatarLegacy(Ljavacard/framework/APDU;)V {
			.stack 5;
			.locals 5;

			.descriptor	Ljavacard/framework/APDU;	0.10;

				L0:	getfield_a_this 0;		// reference thegym/thegym.pin
					invokevirtual 83;		// javacard/framework/OwnerPIN.isValidated()Z
					ifne L2;
				L1:	sspush 27010;
					invokestatic 55;		// javacard/framework/ISOException.throwIt(S)V
				L2:	aload_1;
					invokevirtual 53;		// javacard/framework/APDU.getBuffer()[B
					astore_2;
				L3:	aload_2;
					sconst_2;
					baload;
					sspush 255;
					sand;
					sstore_3;
				L4:	aload_2;
					sconst_3;
					baload;
					sspush 255;
					sand;
					sstore 4;
				L5:	sload_3;
					bspush 8;
					sshl;
					sload 4;
					sor;
					sstore 5;
				L6:	aload_1;
					invokevirtual 85;		// javacard/framework/APDU.setIncomingAndReceive()S
					sstore 6;
				L7:	sload 5;
					sload 6;
					sadd;
					sspush 10240;
					if_scmple L9;
				L8:	sspush 27268;
					invokestatic 55;		// javacard/framework/ISOException.throwIt(S)V
				L9:	aload_2;
					sconst_5;
					getfield_a_this 3;		// reference thegym/thegym.avatarData
					sload 5;
					sload 6;
					invokestatic 50;		// javacard/framework/Util.arrayCopy([BS[BSS)S
					pop;
					sload 5;
					sload 6;
					sadd;
					getfield_s_this 27;		// short thegym/thegym.avatarCurrentSize
					if_scmple L11;
				L10:	aload_0;
					sload 5;
					sload 6;
					sadd;
					putfield_s 27;		// short thegym/thegym.avatarCurrentSize
				L11:	return;
		}

		.method private processGetAvatarLegacy(Ljavacard/framework/APDU;)V {
			.stack 5;
			.locals 6;

			.descriptor	Ljavacard/framework/APDU;	0.10;

				L0:	aload_1;
					invokevirtual 53;		// javacard/framework/APDU.getBuffer()[B
					astore_2;
				L1:	aload_2;
					sconst_2;
					baload;
					sspush 255;
					sand;
					sstore_3;
				L2:	aload_2;
					sconst_3;
					baload;
					sspush 255;
					sand;
					sstore 4;
				L3:	sload_3;
					bspush 8;
					sshl;
					sload 4;
					sor;
					sstore 5;
				L4:	getfield_s_this 27;		// short thegym/thegym.avatarCurrentSize
					ifne L6;
				L5:	aload_1;
					sconst_0;
					sconst_0;
					invokevirtual 84;		// javacard/framework/APDU.setOutgoingAndSend(SS)V
					return;
				L6:	sload 5;
					getfield_s_this 27;		// short thegym/thegym.avatarCurrentSize
					if_scmplt L8;
				L7:	sspush 27264;
					invokestatic 55;		// javacard/framework/ISOException.throwIt(S)V
				L8:	getfield_s_this 27;		// short thegym/thegym.avatarCurrentSize
					sload 5;
					ssub;
					sstore 6;
				L9:	sload 6;
					sspush 128;
					if_scmple L11;
				L10:	sspush 128;
					goto L12;
				L11:	sload 6;
				L12:	sstore 7;
				L13:	getfield_a_this 3;		// reference thegym/thegym.avatarData
					sload 5;
					aload_2;
					sconst_0;
					sload 7;
					invokestatic 50;		// javacard/framework/Util.arrayCopy([BS[BSS)S
					pop;
					aload_1;
					sconst_0;
					sload 7;
					invokevirtual 84;		// javacard/framework/APDU.setOutgoingAndSend(SS)V
					return;
		}

	}

}
